{"type": "FeatureCollection", "features": [{"type": "Feature", "geometry": {"type": "Point", "coordinates": [-73.99519089999998, 40.726821900000004]}, "properties": {"dc_title_s": "Charley Grovesteen: Champion Concert Saloon", "ark": "fk40k2pd18", "id": "6146", "Geometry Type": "Point", "Location": "New York, NY", "Year": "null", "Language": "eng", "Street Address (If Available)": "654 Broadway, Manhattan, Ny", "Subject Terms": "Bars (drinking Establishments)|Advertising Cards|Jewish Merchants|Jewish Peddlers"}}]}