{"type": "FeatureCollection", "features": [{"type": "Feature", "geometry": {"type": "Point", "coordinates": [-74.17086710000001, 40.73866509999999]}, "properties": {"dc_title_s": "Joseph Cohen: Fine Jewelry", "ark": "fk40g40058", "id": "5718", "Geometry Type": "Point", "Location": "Newark, NJ", "Year": "null", "Language": "eng", "Street Address (If Available)": "683 Broad Street, Newark, Nj", "Subject Terms": "Jewelers|Advertising Cards|Jewish Merchants|Jewish Peddlers"}}]}