{"type": "FeatureCollection", "features": [{"type": "Feature", "geometry": {"type": "Point", "coordinates": [-73.9712488, 40.7830603]}, "properties": {"dc_title_s": "Straus: Bargains In Underwear, Knit Jackets, Hoods, Leggins, Mittens, Hose And Gloves", "ark": "fk40z7gz64", "id": "6955", "Geometry Type": "Point", "Location": "New York, NY", "Year": "1884", "Language": "eng", "Street Address (If Available)": "Manhattan, Ny", "Subject Terms": "Glove Industry|Advertising Cards|Jewish Merchants|Jewish Peddlers|Underwear Industry|Hosiery Industry|Leggings|Jackets|Knit Goods"}}]}