{"type": "FeatureCollection", "features": [{"type": "Feature", "geometry": {"type": "Point", "coordinates": [-72.92612379999998, 41.303731200000016]}, "properties": {"dc_title_s": "F. Loewenstein: Tailor, Clothes Cut And Made, Trimmings Furnished", "ark": "fk40p1ct07", "id": "2407", "Geometry Type": "Point", "Location": "New Haven, CT", "Year": "null", "Language": "eng", "Street Address (If Available)": "Basement Of 83 George Street, Near Church, New Haven, Ct", "Subject Terms": "Tailoring|Advertising Cards|Jewish Merchants|Jewish Peddlers|Clothing Trade|Textile Industry|Garment Cutting|Clothing And Dress--remaking"}}]}