{"type": "FeatureCollection", "features": [{"type": "Feature", "geometry": {"type": "Point", "coordinates": [-87.6276531, 41.87959370000003]}, "properties": {"dc_title_s": "Rosenback & Levy: Palais Royal Exclusive Glove Depot", "ark": "fk40p1cs0r", "id": "12136", "Geometry Type": "Point", "Location": "Chicago, IL", "Year": "null", "Language": "eng", "Street Address (If Available)": "159 State Street, Near Monroe, Chicago, Il", "Subject Terms": "Glove Industry|Advertising Cards|Jewish Merchants|Jewish Peddlers|Stores, Retail"}}]}