{"type": "FeatureCollection", "features": [{"type": "Feature", "geometry": {"type": "Point", "coordinates": [-73.68992639999999, 42.73286390000001]}, "properties": {"dc_title_s": "Julius Saul: Clothier", "ark": "fk40v8sk5m", "id": "9592", "Geometry Type": "Point", "Location": "Troy, NY", "Year": "null", "Language": "eng", "Street Address (If Available)": "324 & 326 River Street, Troy, Ny", "Subject Terms": "Clothing Trade|Advertising Cards|Jewish Merchants|Jewish Peddlers|Stores, Retail"}}]}