{"type": "FeatureCollection", "features": [{"type": "Feature", "geometry": {"type": "Point", "coordinates": [-76.151373, 43.05005200000001]}, "properties": {"dc_title_s": "Jacob Straus, With A. Stern: Wholesale & Retail Dealer In Watches, Jewelry & Silver Ware", "ark": "fk4086k77v", "id": "2743", "Geometry Type": "Point", "Location": "Syracuse, NY", "Year": "null", "Language": "eng", "Street Address (If Available)": "Bastable Block, Opposite Post Office, Corner Of Warren & Genesee Streets, Syracuse, Ny", "Subject Terms": "Distributors (commerce)|Advertising Cards|Jewish Merchants|Jewish Peddlers|Dealers (retail Trade)|Clock And Watch Industry|Jewelers|Stores, Retail|Silverware"}}]}