{"type": "FeatureCollection", "features": [{"type": "Feature", "geometry": {"type": "Point", "coordinates": [-74.76461599999999, 40.2196]}, "properties": {"dc_title_s": "A. Lowenstein: Clothier", "ark": "fk40z7gz22", "id": "6018", "Geometry Type": "Point", "Location": "Trenton, NJ", "Year": "null", "Language": "eng", "Street Address (If Available)": "Opposite Opera House, Trenton, Nj", "Subject Terms": "Clothing Trade|Advertising Cards|Jewish Merchants|Jewish Peddlers|Stores, Retail"}}]}