{"type": "FeatureCollection", "features": [{"type": "Feature", "geometry": {"type": "Point", "coordinates": [-71.0636534, 42.350544600000035]}, "properties": {"dc_title_s": "Wyman's: New Cafe", "ark": "fk40z7gz1j", "id": "13431", "Geometry Type": "Point", "Location": "Boston, MA", "Year": "null", "Language": "eng", "Street Address (If Available)": "737 Washington Street, Boston, Ma", "Subject Terms": "Restaurateurs|Advertising Cards|Jewish Merchants|Jewish Peddlers"}}]}