{"type": "FeatureCollection", "features": [{"type": "Feature", "geometry": {"type": "Point", "coordinates": [-75.39823259999999, 40.002160599999996]}, "properties": {"dc_title_s": "Albert B. Katz", "ark": "fk40k2pd7c", "id": "2884", "Geometry Type": "Point", "Location": "Philadelphia, PA", "Year": "null", "Language": "eng", "Street Address (If Available)": "null", "Subject Terms": "Advertising Cards|Jewish Merchants|Jewish Peddlers"}}]}