{"type": "FeatureCollection", "features": [{"type": "Feature", "geometry": {"type": "Point", "coordinates": [-76.56613329999999, 42.93179020000002]}, "properties": {"dc_title_s": "S. Rosenbloom & Sons: Boots And Shoes", "ark": "fk40c58m7v", "id": "7324", "Geometry Type": "Point", "Location": "Auburn, NY", "Year": "null", "Language": "eng", "Street Address (If Available)": "Corner Of Genesee And North Streets, Auburn, Ny", "Subject Terms": "Shoe Industry|Advertising Cards|Jewish Merchants|Jewish Peddlers|Boots"}}]}