{"type": "FeatureCollection", "features": [{"type": "Feature", "geometry": {"type": "Point", "coordinates": [-76.6196458, 39.28844150000002]}, "properties": {"dc_title_s": "J. Rosenblatt & Co.: Importers: Earthenware, China, Majolica, Novelties", "ark": "fk41z4hw0m", "id": "2503", "Geometry Type": "Point", "Location": "Baltimore, MD", "Year": "null", "Language": "eng", "Street Address (If Available)": "32 South Howard Street, Baltimore, Md", "Subject Terms": "Imports|Advertising Cards|Jewish Merchants|Jewish Peddlers|Novelties|Porcelain Industry|Pottery|Majolica"}}]}