{"type": "FeatureCollection", "features": [{"type": "Feature", "geometry": {"type": "Point", "coordinates": [-90.06828489999998, 29.952493800000013]}, "properties": {"dc_title_s": "Rice, Born & Co: Stoves And Ranges", "ark": "fk41n8dp0m", "id": "12808", "Geometry Type": "Point", "Location": "New Orleans, LA", "Year": "null", "Language": "eng", "Street Address (If Available)": "77, 79, & 81 Camp Street, New Orleans, La", "Subject Terms": "Stove Industry And Trade|Advertising Cards|Jewish Merchants|Jewish Peddlers"}}]}