{"type": "FeatureCollection", "features": [{"type": "Feature", "geometry": {"type": "Point", "coordinates": [-78.8696908, 42.88980720000001]}, "properties": {"dc_title_s": "Joseph Gross: Jeweler", "ark": "fk41266b8z", "id": "857", "Geometry Type": "Point", "Location": "Buffalo, NY", "Year": "null", "Language": "eng", "Street Address (If Available)": "113 East Genesee Street, Buffalo, Ny", "Subject Terms": "Jewelers|Advertising Cards|Jewish Merchants|Jewish Peddlers"}}]}