{"type": "FeatureCollection", "features": [{"type": "Feature", "geometry": {"type": "Point", "coordinates": [-71.0616387, 42.355969]}, "properties": {"dc_title_s": "M.M. Cohen: Fashionable Hair Emporium", "ark": "fk41g10x0t", "id": "2555", "Geometry Type": "Point", "Location": "Boston, MA", "Year": "null", "Language": "eng", "Street Address (If Available)": "28 Winter Street, Boston, Ma", "Subject Terms": "Sale Of Human Hair|Advertising Cards|Jewish Merchants|Jewish Peddlers|Stores, Retail"}}]}