{"type": "FeatureCollection", "features": [{"type": "Feature", "geometry": {"type": "Point", "coordinates": [-78.8733712, 42.887668500000004]}, "properties": {"dc_title_s": "Morgenstern: The Hatter", "ark": "fk41n8dp77", "id": "881", "Geometry Type": "Point", "Location": "Buffalo, NY", "Year": "null", "Language": "eng", "Street Address (If Available)": "515 Main Street, Buffalo, Ny", "Subject Terms": "Hat Trade|Advertising Cards|Jewish Merchants|Jewish Peddlers"}}]}