{"type": "FeatureCollection", "features": [{"type": "Feature", "geometry": {"type": "Point", "coordinates": [-75.4968152, 44.6971564]}, "properties": {"dc_title_s": "Nathan Frank: Dry Goods", "ark": "fk41j9q94p", "id": "8226", "Geometry Type": "Point", "Location": "Ogdensburg, NY", "Year": "null", "Language": "eng", "Street Address (If Available)": "3 Eagle Block, Ford Street, Ogdensburg, Ny", "Subject Terms": "Dry-goods|Advertising Cards|Jewish Merchants|Jewish Peddlers|Stores, Retail"}}]}