{"type": "FeatureCollection", "features": [{"type": "Feature", "geometry": {"type": "Point", "coordinates": [-73.99204119999999, 40.738829100000004]}, "properties": {"dc_title_s": "Alois Kohn & Co.: Manufacturers Of Solid Gold Chains", "ark": "fk41266c09", "id": "6117", "Geometry Type": "Point", "Location": "New York, NY", "Year": "null", "Language": "eng", "Street Address (If Available)": "16-18 Maiden Lane, Near Broadway, Manhattan, Ny", "Subject Terms": "Manufactures|Advertising Cards|Jewish Merchants|Jewish Peddlers|Gold Jewelry|Necklace|Chains"}}]}