{"type": "FeatureCollection", "features": [{"type": "Feature", "geometry": {"type": "Point", "coordinates": [-73.7535928, 42.647401900000006]}, "properties": {"dc_title_s": "E. Frank: Dealer In Boots, Shoes And Slippers", "ark": "fk41g10w7z", "id": "7112", "Geometry Type": "Point", "Location": "Albany, NY", "Year": "null", "Language": "eng", "Street Address (If Available)": "76 South Pearl Street, Albany, Ny", "Subject Terms": "Dealers (retail Trade)|Advertising Cards|Jewish Merchants|Jewish Peddlers|Shoe Industry|Boots|Stores, Retail|Shoe Store|Slipper Industry"}}]}