{"type": "FeatureCollection", "features": [{"type": "Feature", "geometry": {"type": "Point", "coordinates": [-76.15094150000002, 43.05033370000004]}, "properties": {"dc_title_s": "S. Rosenbloom & Sons: Fine Shoes", "ark": "fk42f81t79", "id": "9981", "Geometry Type": "Point", "Location": "Syracuse, NY", "Year": "null", "Language": "eng", "Street Address (If Available)": "17 & 19 East Water Street, Hanover Square, Syracuse, Ny", "Subject Terms": "Shoe Industry|Advertising Cards|Jewish Merchants|Jewish Peddlers"}}]}