{"type": "FeatureCollection", "features": [{"type": "Feature", "geometry": {"type": "Point", "coordinates": [-69.8162597, 43.9144675]}, "properties": {"dc_title_s": "S.J. Goldstein: Clothier", "ark": "fk42z1jq9d", "id": "12583", "Geometry Type": "Point", "Location": "Bath, ME", "Year": "null", "Language": "eng", "Street Address (If Available)": "Church Block, Bath, Me", "Subject Terms": "Clothing Trade|Advertising Cards|Jewish Merchants|Jewish Peddlers|Stores, Retail"}}]}