{"type": "FeatureCollection", "features": [{"type": "Feature", "geometry": {"type": "Point", "coordinates": [-87.908762, 43.03549219999999]}, "properties": {"dc_title_s": "Julius Lando: Optician", "ark": "fk42b9bd27", "id": "13809", "Geometry Type": "Point", "Location": "Milwaukee, WI", "Year": "null", "Language": "eng", "Street Address (If Available)": "436 East Water Street, Milwaukee, Wi", "Subject Terms": "Opticians|Advertising Cards|Jewish Merchants|Jewish Peddlers"}}]}