{"type": "FeatureCollection", "features": [{"type": "Feature", "geometry": {"type": "Point", "coordinates": [-74.3437467, 43.0528506]}, "properties": {"dc_title_s": "Cohen Bros.: Big Grocery", "ark": "fk42n5fk6t", "id": "8822", "Geometry Type": "Point", "Location": "Gloversville, NY", "Year": "null", "Language": "eng", "Street Address (If Available)": "Gloversville, Ny", "Subject Terms": "Grocers|Advertising Cards|Jewish Merchants|Jewish Peddlers|Stores, Retail"}}]}