{"type": "FeatureCollection", "features": [{"type": "Feature", "geometry": {"type": "Point", "coordinates": [-76.14217719999999, 40.814120599999995]}, "properties": {"dc_title_s": "J.F. Hursh: The Kaier", "ark": "fk42f81t58", "id": "2867", "Geometry Type": "Point", "Location": "Mahanoy, PA", "Year": "null", "Language": "eng", "Street Address (If Available)": "41-43 North Main Street, Mahanoy, Pa", "Subject Terms": "Hotelkeeper|Advertising Cards|Jewish Merchants|Jewish Peddlers"}}]}