{"type": "FeatureCollection", "features": [{"type": "Feature", "geometry": {"type": "Point", "coordinates": [-80.7209149, 40.0639616]}, "properties": {"dc_title_s": "Bloch Brothers: Tobacco", "ark": "fk43n2gg0t", "id": "13139", "Geometry Type": "Point", "Location": "Wheeling, WV", "Year": "null", "Language": "eng", "Street Address (If Available)": "Wheeling, Wv", "Subject Terms": "Tobacco Industry|Advertising Cards|Jewish Merchants|Jewish Peddlers"}}]}