{"type": "FeatureCollection", "features": [{"type": "Feature", "geometry": {"type": "Point", "coordinates": [-73.99401559999998, 40.72037590000001]}, "properties": {"dc_title_s": "Hershfield & Silverstone: Shirt Makers And Men's Furnishers", "ark": "fk43f52q3b", "id": "8980", "Geometry Type": "Point", "Location": "New York, NY", "Year": "null", "Language": "eng", "Street Address (If Available)": "170 Bowery, Between Broome & Spring Streets, New York, Ny", "Subject Terms": "Men's Furnishing Goods|Advertising Cards|Jewish Merchants|Jewish Peddlers|Shirt Industry|Clothing Trade"}}]}