{"type": "FeatureCollection", "features": [{"type": "Feature", "geometry": {"type": "Point", "coordinates": [-95.93713779999999, 41.26286999999998]}, "properties": {"dc_title_s": "F.H. Schwartz: Shoe Dealer", "ark": "fk4377nw5z", "id": "12539", "Geometry Type": "Point", "Location": "Omaha, NE", "Year": "null", "Language": "eng", "Street Address (If Available)": "416 North Sixteenth Street, Omaha, Ne", "Subject Terms": "Dealers (retail Trade)|Advertising Cards|Jewish Merchants|Jewish Peddlers|Shoe Industry|Stores, Retail|Shoe Store"}}]}