{"type": "FeatureCollection", "features": [{"type": "Feature", "geometry": {"type": "Point", "coordinates": [-91.41120349999998, 39.93323910000002]}, "properties": {"dc_title_s": "J.D. Levy & Co.: Clothiers", "ark": "fk43t9w735", "id": "12292", "Geometry Type": "Point", "Location": "Quincy, IL", "Year": "null", "Language": "eng", "Street Address (If Available)": "313 & 315 Hampshire Street, Quincy, Il", "Subject Terms": "Clothing Trade|Advertising Cards|Jewish Merchants|Jewish Peddlers|Stores, Retail"}}]}