{"type": "FeatureCollection", "features": [{"type": "Feature", "geometry": {"type": "Point", "coordinates": [-71.06044969999999, 42.35800210000002]}, "properties": {"dc_title_s": "N.A. Moses: Fine Boots And Shoes", "ark": "fk4377nw70", "id": "13351", "Geometry Type": "Point", "Location": "Boston, MA", "Year": "null", "Language": "eng", "Street Address (If Available)": "43 Tremont Street, Boston, Ma", "Subject Terms": "Shoe Industry|Advertising Cards|Jewish Merchants|Jewish Peddlers|Boots"}}]}