{"type": "FeatureCollection", "features": [{"type": "Feature", "geometry": {"type": "Point", "coordinates": [-78.86638000000002, 42.887456]}, "properties": {"dc_title_s": "Reiss: Tailor", "ark": "fk44f23m0w", "id": "887", "Geometry Type": "Point", "Location": "Buffalo, NY", "Year": "null", "Language": "eng", "Street Address (If Available)": "192 Broadway, Buffalo, Ny", "Subject Terms": "Tailoring|Advertising Cards|Jewish Merchants|Jewish Peddlers"}}]}