{"type": "FeatureCollection", "features": [{"type": "Feature", "geometry": {"type": "Point", "coordinates": [-73.9992621, 40.744640700000005]}, "properties": {"dc_title_s": "H. Gershel & Bro.: Cloaks, Mantillas, And Fancy Furs", "ark": "fk44j0t00x", "id": "6209", "Geometry Type": "Point", "Location": "New York, NY", "Year": "null", "Language": "eng", "Street Address (If Available)": "233 Eighth Avenue, Between 22nd And 23rd Streets, Manhattan, Ny", "Subject Terms": "Fur Trade|Advertising Cards|Jewish Merchants|Jewish Peddlers|Cloaks|Shawl Industry|Lace Industry|Silk Industry"}}]}