{"type": "FeatureCollection", "features": [{"type": "Feature", "geometry": {"type": "Point", "coordinates": [-84.51544819999998, 39.1003812]}, "properties": {"dc_title_s": "Hyman & Co.: Furniture, Carpets, Stoves, Etc.", "ark": "fk44m9hd3q", "id": "10286", "Geometry Type": "Point", "Location": "Cincinnati, OH", "Year": "null", "Language": "eng", "Street Address (If Available)": "155, 157, & 159 West Fifth Street, Between Race And Elm, Cincinnati, Oh", "Subject Terms": "Rug And Carpet Industry|Advertising Cards|Jewish Merchants|Jewish Peddlers|Furniture Industry And Trade|Stove Industry And Trade"}}]}