{"type": "FeatureCollection", "features": [{"type": "Feature", "geometry": {"type": "Point", "coordinates": [-90.18917, 38.627453700000004]}, "properties": {"dc_title_s": "A. Siegel Gas Fixture Co.: Plumbers, Gas And Steam Fitters", "ark": "fk44f23k2f", "id": "12417", "Geometry Type": "Point", "Location": "St. Louis, MO", "Year": "null", "Language": "eng", "Street Address (If Available)": "219 North Broadway, St. Louis, Mo", "Subject Terms": "Gas-fitting|Advertising Cards|Jewish Merchants|Jewish Peddlers|Plumbing Industry|Steam-pipes"}}]}