{"type": "FeatureCollection", "features": [{"type": "Feature", "geometry": {"type": "Point", "coordinates": [-74.0018566, 40.70775990000001]}, "properties": {"dc_title_s": "Begloff Fish Co., Inc.", "ark": "fk44460d7h", "id": "6130", "Geometry Type": "Point", "Location": "New York, NY", "Year": "null", "Language": "eng", "Street Address (If Available)": "28 Peck Slip, Manhattan, Ny", "Subject Terms": "Fish Trade|Advertising Cards|Jewish Merchants|Jewish Peddlers"}}]}