{"type": "FeatureCollection", "features": [{"type": "Feature", "geometry": {"type": "Point", "coordinates": [-87.62979819999998, 41.87811360000002]}, "properties": {"dc_title_s": "Rothschild Bros.: Raworth, Schodde & Co.'s Wool Soap", "ark": "fk44f23k1x", "id": "12148", "Geometry Type": "Point", "Location": "Chicago, IL", "Year": "null", "Language": "eng", "Street Address (If Available)": "Chicago, Il", "Subject Terms": "Soap Trade|Advertising Cards|Jewish Merchants|Jewish Peddlers|Woolen Goods Industry"}}]}