{"type": "FeatureCollection", "features": [{"type": "Feature", "geometry": {"type": "Point", "coordinates": [-74.00479889999998, 40.7149476]}, "properties": {"dc_title_s": "Kaufmann & Strauss: Art Publishers", "ark": "fk44t6x53r", "id": "9016", "Geometry Type": "Point", "Location": "New York, NY", "Year": "null", "Language": "eng", "Street Address (If Available)": "75 And 77 Duane Street, New York, Ny", "Subject Terms": "Art Publishing|Advertising Cards|Jewish Merchants|Jewish Peddlers"}}]}