{"type": "FeatureCollection", "features": [{"type": "Feature", "geometry": {"type": "Point", "coordinates": [-71.41137569999998, 41.82381649999999]}, "properties": {"dc_title_s": "S. Milkman & Co.: Millinery And Hair Goods", "ark": "fk45t3z15d", "id": "12708", "Geometry Type": "Point", "Location": "Providence, RI", "Year": "null", "Language": "eng", "Street Address (If Available)": "161 Westminster Street, Providence, Ri", "Subject Terms": "Millinery|Advertising Cards|Jewish Merchants|Jewish Peddlers|Hair|Stores, Retail"}}]}