{"type": "FeatureCollection", "features": [{"type": "Feature", "geometry": {"type": "Point", "coordinates": [-71.0773221, 42.370495700000006]}, "properties": {"dc_title_s": "Louis Cohen: Merchant Tailor", "ark": "fk45q57n3b", "id": "13442", "Geometry Type": "Point", "Location": "East Cambridge, MA", "Year": "null", "Language": "eng", "Street Address (If Available)": "106 Cambridge Street, East Cambridge, Ma", "Subject Terms": "Clothing Trade|Advertising Cards|Jewish Merchants|Jewish Peddlers|Textile Industry|Tailoring"}}]}