{"type": "FeatureCollection", "features": [{"type": "Feature", "geometry": {"type": "Point", "coordinates": [-93.26698340000002, 44.98059110000003]}, "properties": {"dc_title_s": "Loewenstine & Co.: One Price Clothing House", "ark": "fk4571qp97", "id": "13730", "Geometry Type": "Point", "Location": "Minneapolis, MN", "Year": "null", "Language": "eng", "Street Address (If Available)": "107 Washington Avenue South, Minneapolis, Mn", "Subject Terms": "Clothing Trade|Advertising Cards|Jewish Merchants|Jewish Peddlers|Stores, Retail"}}]}