{"type": "FeatureCollection", "features": [{"type": "Feature", "geometry": {"type": "Point", "coordinates": [-76.8008004, 42.08864000000001]}, "properties": {"dc_title_s": "Freudenheim & Abramson: Jewelers", "ark": "fk45149x96", "id": "8715", "Geometry Type": "Point", "Location": "Elmira, NY", "Year": "null", "Language": "eng", "Street Address (If Available)": "102 Lake Street, Elmira, Ny", "Subject Terms": "Jewelers|Advertising Cards|Jewish Merchants|Jewish Peddlers"}}]}