{"type": "FeatureCollection", "features": [{"type": "Feature", "geometry": {"type": "Point", "coordinates": [-94.5632932, 39.09925960000001]}, "properties": {"dc_title_s": "Julius Cahn: Dealer In Wood, Hard And Soft Coal", "ark": "fk45149x2k", "id": "12397", "Geometry Type": "Point", "Location": "Kansas City, MO", "Year": "null", "Language": "eng", "Street Address (If Available)": "1519 East 12th Street, Kansas City, Mo", "Subject Terms": "Dealers (retail Trade)|Advertising Cards|Jewish Merchants|Jewish Peddlers|Lumber Trade|Coal Trade"}}]}