{"type": "FeatureCollection", "features": [{"type": "Feature", "geometry": {"type": "Point", "coordinates": [-73.9441579, 40.67817840000001]}, "properties": {"dc_title_s": "H. Seidenberg: Manufacturer: The After-lunch Cigarettes", "ark": "fk46t0zz1g", "id": "6215", "Geometry Type": "Point", "Location": "Brooklyn, NY", "Year": "null", "Language": "eng", "Street Address (If Available)": "Brooklyn, Ny", "Subject Terms": "Cigarette Industry|Advertising Cards|Jewish Merchants|Jewish Peddlers|Tobacco|Tobacco Industry|Cigarette Industry"}}]}