{"type": "FeatureCollection", "features": [{"type": "Feature", "geometry": {"type": "Point", "coordinates": [-73.84870420000001, 43.002222200000034]}, "properties": {"dc_title_s": "Frank & Levy: Dealers In Clothing", "ark": "fk46q28j81", "id": "782", "Geometry Type": "Point", "Location": "Ballston Spa, NY", "Year": "null", "Language": "eng", "Street Address (If Available)": "30 & 32 Milton Avenue, Ballston Spa, Ny", "Subject Terms": "Clothing Trade|Advertising Cards|Jewish Merchants|Jewish Peddlers|Stores, Retail"}}]}