{"type": "FeatureCollection", "features": [{"type": "Feature", "geometry": {"type": "Point", "coordinates": [-90.06859319999998, 29.952999600000012]}, "properties": {"dc_title_s": "F. Oberheuser: Merchant Tailor", "ark": "fk4611bv1n", "id": "2458", "Geometry Type": "Point", "Location": "New Orleans, LA", "Year": "null", "Language": "eng", "Street Address (If Available)": "18 Exchange Place, New Orleans, La", "Subject Terms": "Clothing Trade|Advertising Cards|Jewish Merchants|Jewish Peddlers|Textile Industry|Tailoring"}}]}