{"type": "FeatureCollection", "features": [{"type": "Feature", "geometry": {"type": "Point", "coordinates": [-73.7528796, 42.648844100000005]}, "properties": {"dc_title_s": "Jos. Mandelbaum: Boots & Shoes", "ark": "fk4697g04f", "id": "7173", "Geometry Type": "Point", "Location": "Albany, NY", "Year": "null", "Language": "eng", "Street Address (If Available)": "20 South Pearl Street, Opposite Howard Street (miller's Building), Albany, Ny", "Subject Terms": "Shoe Industry|Advertising Cards|Jewish Merchants|Jewish Peddlers|Boots"}}]}