{"type": "FeatureCollection", "features": [{"type": "Feature", "geometry": {"type": "Point", "coordinates": [-93.252711, 44.974785999999995]}, "properties": {"dc_title_s": "Mrs. H.G. Blum: Dress Making And Millinery", "ark": "fk4668rm2z", "id": "13735", "Geometry Type": "Point", "Location": "Minneapolis, MN", "Year": "null", "Language": "eng", "Street Address (If Available)": "1113 Washington Avenue South, Minneapolis, Mn", "Subject Terms": "Millinery|Advertising Cards|Jewish Merchants|Jewish Peddlers|Dressmaking"}}]}