{"type": "FeatureCollection", "features": [{"type": "Feature", "geometry": {"type": "Point", "coordinates": [-73.9847501, 40.724954999999994]}, "properties": {"dc_title_s": "Berliner Brothers: Dry Goods", "ark": "fk46d65c8h", "id": "7730", "Geometry Type": "Point", "Location": "New York, NY", "Year": "null", "Language": "eng", "Street Address (If Available)": "75 Avenue A, New York, Ny", "Subject Terms": "Dry-goods|Advertising Cards|Jewish Merchants|Jewish Peddlers|Stores, Retail"}}]}