{"type": "FeatureCollection", "features": [{"type": "Feature", "geometry": {"type": "Point", "coordinates": [-75.2267408, 43.103994]}, "properties": {"dc_title_s": "Jos. Wineburgh & Son: Diamonds, Watches, Fine Jewelry", "ark": "fk46402713", "id": "9353", "Geometry Type": "Point", "Location": "Utica, NY", "Year": "null", "Language": "eng", "Street Address (If Available)": "32 Genessee Street, Utica, Ny", "Subject Terms": "Diamond Industry And Trade|Advertising Cards|Jewish Merchants|Jewish Peddlers|Clock And Watch Makers|Jewelers"}}]}