{"type": "FeatureCollection", "features": [{"type": "Feature", "geometry": {"type": "Point", "coordinates": [-74.0077834, 40.726451499999996]}, "properties": {"dc_title_s": "Cohen & Grabowski: Merchant Tailors", "ark": "fk4708cq4k", "id": "7767", "Geometry Type": "Point", "Location": "New York, NY", "Year": "null", "Language": "eng", "Street Address (If Available)": "317 Hudson Street Between Vandam And Spring Streets, New York, Ny", "Subject Terms": "Clothing Trade|Advertising Cards|Jewish Merchants|Jewish Peddlers|Textile Industry|Tailoring"}}]}