{"type": "FeatureCollection", "features": [{"type": "Feature", "geometry": {"type": "Point", "coordinates": [-73.688333, 42.7287319]}, "properties": {"dc_title_s": "Morris Gross: Clothier", "ark": "fk47p99g49", "id": "9749", "Geometry Type": "Point", "Location": "Troy, NY", "Year": "null", "Language": "eng", "Street Address (If Available)": "123 Congress Street, Troy, Ny", "Subject Terms": "Clothing Trade|Advertising Cards|Jewish Merchants|Jewish Peddlers|Stores, Retail"}}]}