{"type": "FeatureCollection", "features": [{"type": "Feature", "geometry": {"type": "Point", "coordinates": [-76.14558779999999, 43.0362102]}, "properties": {"dc_title_s": "J.L. Liberman: Fine Watches, Jewelry, Silverware & Spectacles", "ark": "fk4794gw7n", "id": "9282", "Geometry Type": "Point", "Location": "Syracuse, NY", "Year": "1883", "Language": "eng", "Street Address (If Available)": "103 Grape Street, Syracuse, Ny", "Subject Terms": "Clock And Watch Industry|Advertising Cards|Jewish Merchants|Jewish Peddlers|Jewelers|Silverware|Eyeglasses"}}]}