{"type": "FeatureCollection", "features": [{"type": "Feature", "geometry": {"type": "Point", "coordinates": [-74.784738, 40.22801900000002]}, "properties": {"dc_title_s": "Morris May: Watches And Jewelry", "ark": "fk47h1wn9q", "id": "6042", "Geometry Type": "Point", "Location": "Trenton, NJ", "Year": "null", "Language": "eng", "Street Address (If Available)": "25 South Greene Street, Trenton, Nj", "Subject Terms": "Clock And Watch Makers|Advertising Cards|Jewish Merchants|Jewish Peddlers|Jewelers"}}]}