{"type": "FeatureCollection", "features": [{"type": "Feature", "geometry": {"type": "Point", "coordinates": [-73.98853929999999, 40.71632700000002]}, "properties": {"dc_title_s": "Joseph Weinberg", "ark": "fk47d3690z", "id": "6286", "Geometry Type": "Point", "Location": "New York, NY", "Year": "null", "Language": "eng", "Street Address (If Available)": "370 Grand Street, Manhattan, Ny", "Subject Terms": "Clothing Trade|Advertising Cards|Jewish Merchants|Jewish Peddlers|Men's Furnishing Goods|Hosiery Industry|Glove Industry|Women's Clothing Industry|Distributors (commerce)|Stores, Retail"}}]}