{"type": "FeatureCollection", "features": [{"type": "Feature", "geometry": {"type": "Point", "coordinates": [-87.02585939999999, 41.31670580000001]}, "properties": {"dc_title_s": "H. Rosenbaum: Dry Goods, Boots Shoes Etc", "ark": "fk4708cp9p", "id": "12339", "Geometry Type": "Point", "Location": "Kouts, IN", "Year": "null", "Language": "eng", "Street Address (If Available)": "Koutts, In", "Subject Terms": "Dry-goods|Advertising Cards|Jewish Merchants|Jewish Peddlers|Stores, Retail|Shoe Store|Shoe Industry|Boots"}}]}