{"type": "FeatureCollection", "features": [{"type": "Feature", "geometry": {"type": "Point", "coordinates": [-73.7852804, 43.0808631]}, "properties": {"dc_title_s": "A. Bornefeld: Jeweler", "ark": "fk47s80v49", "id": "9136", "Geometry Type": "Point", "Location": "Saratoga Springs, NY", "Year": "null", "Language": "eng", "Street Address (If Available)": "376 Broadway, Saratoga Springs, Ny", "Subject Terms": "Jewelers|Advertising Cards|Jewish Merchants|Jewish Peddlers"}}]}