{"type": "FeatureCollection", "features": [{"type": "Feature", "geometry": {"type": "Point", "coordinates": [-73.94156099999998, 40.673725899999994]}, "properties": {"dc_title_s": "E. Dreyfus: Merchant Tailor", "ark": "fk47h1wp54", "id": "9502", "Geometry Type": "Point", "Location": "Rondout, NY", "Year": "null", "Language": "eng", "Street Address (If Available)": "179 The Strand, Roundout, Ny", "Subject Terms": "Clothing Trade|Advertising Cards|Jewish Merchants|Jewish Peddlers|Children's Clothing Industry|Ready-to-wear Clothing Industry|Merchant|Tailor"}}]}