{"type": "FeatureCollection", "features": [{"type": "Feature", "geometry": {"type": "Point", "coordinates": [-72.67338649999999, 41.7665461]}, "properties": {"dc_title_s": "Freeman's: Suits, Overcoats, Ulsters And Ulsterettes", "ark": "fk4862td7r", "id": "2377", "Geometry Type": "Point", "Location": "Hartford, CT", "Year": "null", "Language": "eng", "Street Address (If Available)": "14 & 16 Asylum Street, Hartford, Ct", "Subject Terms": "Suits (clothing)|Advertising Cards|Jewish Merchants|Jewish Peddlers|Clothing Trade|Coats"}}]}