{"type": "FeatureCollection", "features": [{"type": "Feature", "geometry": {"type": "Point", "coordinates": [-76.15033549999998, 43.048934500000016]}, "properties": {"dc_title_s": "S. Rosenbloom & Sons: Boot And Shoe Dealers", "ark": "fk48d07644", "id": "10123", "Geometry Type": "Point", "Location": "Syracuse, NY", "Year": "null", "Language": "eng", "Street Address (If Available)": "Post Office Building, Syracuse, Ny", "Subject Terms": "Shoe Industry|Advertising Cards|Jewish Merchants|Jewish Peddlers|Boots"}}]}