{"type": "FeatureCollection", "features": [{"type": "Feature", "geometry": {"type": "Point", "coordinates": [-75.2440047, 39.914129]}, "properties": {"dc_title_s": "Fels-naptha: Soap", "ark": "fk48k7mz1x", "id": "257", "Geometry Type": "Point", "Location": "Philadelphia, PA", "Year": "null", "Language": "eng", "Street Address (If Available)": "Philadelphia, Pa", "Subject Terms": "Soap Trade|Advertising Cards|Jewish Merchants|Jewish Peddlers"}}]}