{"type": "FeatureCollection", "features": [{"type": "Feature", "geometry": {"type": "Point", "coordinates": [-80.00087829999998, 40.43710709999999]}, "properties": {"dc_title_s": "Gustav Mark: Wine & Beer Saloon", "ark": "fk48w3r48h", "id": "3044", "Geometry Type": "Point", "Location": "Pittsburgh, PA", "Year": "null", "Language": "eng", "Street Address (If Available)": "19 Smithfield Street, Pittsburgh, Pa", "Subject Terms": "Alcoholic Beverage Industry|Advertising Cards|Jewish Merchants|Jewish Peddlers|Wine Industry|Beer Industry|Bars (drinking Establishments)"}}]}