{"type": "FeatureCollection", "features": [{"type": "Feature", "geometry": {"type": "Point", "coordinates": [-69.44546889999998, 45.253783]}, "properties": {"dc_title_s": "Banghart Bros: Cigars", "ark": "fk48g8xj61", "id": "12620", "Geometry Type": "Point", "Location": "Maine", "Year": "null", "Language": "eng", "Street Address (If Available)": "Maine", "Subject Terms": "Cigar Industry|Advertising Cards|Jewish Merchants|Jewish Peddlers|Tobacco Industry"}}]}