{"type": "FeatureCollection", "features": [{"type": "Feature", "geometry": {"type": "Point", "coordinates": [-76.9995573, 38.9085987]}, "properties": {"dc_title_s": "M. Silver: Millinery, Fancy Goods, Cloakes And Suits", "ark": "fk48344065", "id": "13110", "Geometry Type": "Point", "Location": "Washington, D.C.", "Year": "null", "Language": "eng", "Street Address (If Available)": "715 Market Space, Washington, D.C.", "Subject Terms": "Millinery|Advertising Cards|Jewish Merchants|Jewish Peddlers|Notions (merchandise)|Dry-goods|Stores, Retail|Cloaks|Suits (clothing)|Clothing Trade"}}]}