{"type": "FeatureCollection", "features": [{"type": "Feature", "geometry": {"type": "Point", "coordinates": [-73.75684099999998, 42.65357920000001]}, "properties": {"dc_title_s": "Mandelbaum: Boots, Shoes And Slippers", "ark": "fk48344112", "id": "7232", "Geometry Type": "Point", "Location": "Albany, NY", "Year": "null", "Language": "eng", "Street Address (If Available)": "73 Washington Avenue, Albany, Ny", "Subject Terms": "Shoe Industry|Advertising Cards|Jewish Merchants|Jewish Peddlers|Boots|Slipper Industry"}}]}