{"type": "FeatureCollection", "features": [{"type": "Feature", "geometry": {"type": "Point", "coordinates": [-73.98857799999999, 40.692163100000016]}, "properties": {"dc_title_s": "J. Rothschild: Importer Of French Millinery Goods", "ark": "fk48s51r2c", "id": "811", "Geometry Type": "Point", "Location": "Brooklyn, NY", "Year": "null", "Language": "eng", "Street Address (If Available)": "271 Fulton Street, Brooklyn, Ny", "Subject Terms": "Millinery|Advertising Cards|Jewish Merchants|Jewish Peddlers|Imports"}}]}