{"type": "FeatureCollection", "features": [{"type": "Feature", "geometry": {"type": "Point", "coordinates": [-74.00072519999999, 40.732514699999996]}, "properties": {"dc_title_s": "S. Bloomfield: Fine Shoes", "ark": "fk49314w8v", "id": "8043", "Geometry Type": "Point", "Location": "New York, NY", "Year": "null", "Language": "eng", "Street Address (If Available)": "367 Sixth Avenue, New York, Ny", "Subject Terms": "Shoe Industry|Advertising Cards|Jewish Merchants|Jewish Peddlers"}}]}