{"type": "FeatureCollection", "features": [{"type": "Feature", "geometry": {"type": "Point", "coordinates": [-73.99539619999999, 40.750076100000015]}, "properties": {"dc_title_s": "Peisner's: Millinery", "ark": "fk4902fh9c", "id": "8537", "Geometry Type": "Point", "Location": "New York, NY", "Year": "1881", "Language": "eng", "Street Address (If Available)": "409 Eighth Avenue, Between 30th And 31st Streets, New York, Ny", "Subject Terms": "Millinery|Advertising Cards|Jewish Merchants|Jewish Peddlers"}}]}