{"type": "FeatureCollection", "features": [{"type": "Feature", "geometry": {"type": "Point", "coordinates": [-71.0605177, 42.355450399999995]}, "properties": {"dc_title_s": "A. Shuman & Co.: Boys' Retail Department (hammersmith)", "ark": "fk49s22m41", "id": "13160", "Geometry Type": "Point", "Location": "Boston, MA", "Year": "null", "Language": "eng", "Street Address (If Available)": "440 Washington Street, Boston, Ma", "Subject Terms": "Dealers (retail Trade)|Advertising Cards|Jewish Merchants|Jewish Peddlers|Clothing Trade|Children's Clothing Industry"}}]}