{"type": "FeatureCollection", "features": [{"type": "Feature", "geometry": {"type": "Point", "coordinates": [-71.0569873, 42.35710200000001]}, "properties": {"dc_title_s": "Gustav Rice, With Wood, Pollard & Co.: Wholesale & Retail Dealers In Choice Brands Of Imported & Domestic Cigars", "ark": "fk4902fj27", "id": "2534", "Geometry Type": "Point", "Location": "Boston, MA", "Year": "1885", "Language": "eng", "Street Address (If Available)": "61 Devonshire Street, Opposite New Post Office, Boston, Ma", "Subject Terms": "Distributors (commerce)|Advertising Cards|Jewish Merchants|Jewish Peddlers|Dealers (retail Trade)|Cigar Industry|Tobacco Industry"}}]}