{"type": "FeatureCollection", "features": [{"type": "Feature", "geometry": {"type": "Point", "coordinates": [-73.98601119999998, 40.726606000000004]}, "properties": {"dc_title_s": "Jacob Roth: Dealer In Butter, Cheese And Eggs", "ark": "fk4bg30c43", "id": "6554", "Geometry Type": "Point", "Location": "New York, NY", "Year": "null", "Language": "eng", "Street Address (If Available)": "106 First Avenue, Between 6th & 7th Streets, Manhattan, Ny", "Subject Terms": "Dealers (retail Trade)|Advertising Cards|Jewish Merchants|Jewish Peddlers|Butter Trade|Stores, Retail|Cheese Industry|Egg Trade"}}]}