{"type": "FeatureCollection", "features": [{"type": "Feature", "geometry": {"type": "Point", "coordinates": [-74.1776209, 40.73721379999999]}, "properties": {"dc_title_s": "Sternberg & Sherman: Clothing", "ark": "fk4br93h7f", "id": "5811", "Geometry Type": "Point", "Location": "Newark, NJ", "Year": "null", "Language": "eng", "Street Address (If Available)": "249 Market Street, Newark, Nj", "Subject Terms": "Clothing Trade|Advertising Cards|Jewish Merchants|Jewish Peddlers|Stores, Retail"}}]}