{"type": "FeatureCollection", "features": [{"type": "Feature", "geometry": {"type": "Point", "coordinates": [-77.6123667, 43.15675390000001]}, "properties": {"dc_title_s": "S. Rosenblatt & Co.: Millinery And Furnishings", "ark": "fk4b285t3m", "id": "9447", "Geometry Type": "Point", "Location": "Rochester, NY", "Year": "null", "Language": "eng", "Street Address (If Available)": "42 State Street, Rochester, Ny", "Subject Terms": "Millinery|Advertising Cards|Jewish Merchants|Jewish Peddlers|House Furnishings Industry And Trade"}}]}