{"type": "FeatureCollection", "features": [{"type": "Feature", "geometry": {"type": "Point", "coordinates": [-89.6212271, 42.2966861]}, "properties": {"dc_title_s": "Al. Baumgarten: Salvator Export Beer", "ark": "fk4b85kk1m", "id": "12253", "Geometry Type": "Point", "Location": "Freeport, IL", "Year": "null", "Language": "eng", "Street Address (If Available)": "Freeport, Il", "Subject Terms": "Beer Industry|Advertising Cards|Jewish Merchants|Jewish Peddlers|Alcoholic Beverage Industry|Brewing"}}]}