{"type": "FeatureCollection", "features": [{"type": "Feature", "geometry": {"type": "Point", "coordinates": [-69.8142719, 43.91250320000002]}, "properties": {"dc_title_s": "S.J. Goldstein: Clothier", "ark": "fk4bc48z1m", "id": "12580", "Geometry Type": "Point", "Location": "Bath, ME", "Year": "null", "Language": "eng", "Street Address (If Available)": "Church Block, Front Street, Bath, Me", "Subject Terms": "Clothing Trade|Advertising Cards|Jewish Merchants|Jewish Peddlers|Stores, Retail"}}]}