{"type": "FeatureCollection", "features": [{"type": "Feature", "geometry": {"type": "Point", "coordinates": [-70.33334099999999, 43.678304999999995]}, "properties": {"dc_title_s": "S. Arenovsky: Clothing Store", "ark": "fk4b285s55", "id": "13371", "Geometry Type": "Point", "Location": "Boston, MA", "Year": "null", "Language": "eng", "Street Address (If Available)": "Bridge Street Westbrook, Boston, Ma", "Subject Terms": "Clothing Trade|Advertising Cards|Jewish Merchants|Jewish Peddlers|Stores, Retail"}}]}