{"type": "FeatureCollection", "features": [{"type": "Feature", "geometry": {"type": "Point", "coordinates": [-90.21154989999998, 38.61509500000001]}, "properties": {"dc_title_s": "Mathis & Feldmann's: Dry Goods Store", "ark": "fk4bv7sx0w", "id": "12489", "Geometry Type": "Point", "Location": "St. Louis, MO", "Year": "null", "Language": "eng", "Street Address (If Available)": "1600 & 1602 Carondelet Avenue, Corner Carroll Street, St. Louis, Mo", "Subject Terms": "Dry-goods|Advertising Cards|Jewish Merchants|Jewish Peddlers|Stores, Retail"}}]}