{"type": "FeatureCollection", "features": [{"type": "Feature", "geometry": {"type": "Point", "coordinates": [-74.01181529999998, 40.71290160000001]}, "properties": {"dc_title_s": "Chas. Cohen: Commission Merchant, And Wholesale And Retail Dealer In Poultry, Game, Fruits And Vegetables", "ark": "fk4c53x31q", "id": "6148", "Geometry Type": "Point", "Location": "New York, NY", "Year": "null", "Language": "eng", "Street Address (If Available)": "74 Vesey Street, Manhattan, Ny", "Subject Terms": "Distributors (commerce)|Advertising Cards|Jewish Merchants|Jewish Peddlers|Dealers (retail Trade)|Commission Merchants|Fruit Trade|Produce Trade|Vegetable Trade|Poultry Industry|Stores, Retail"}}]}