{"type": "FeatureCollection", "features": [{"type": "Feature", "geometry": {"type": "Point", "coordinates": [-90.58428659999998, 41.508885500000005]}, "properties": {"dc_title_s": "J.O. Freed: Palace Shoe Store", "ark": "fk4c53x28v", "id": "12315", "Geometry Type": "Point", "Location": "Rock Island, IL", "Year": "null", "Language": "eng", "Street Address (If Available)": "Commercial House Block, Rock Island, Il", "Subject Terms": "Shoe Industry|Advertising Cards|Jewish Merchants|Jewish Peddlers|Stores, Retail|Shoe Store"}}]}