{"type": "FeatureCollection", "features": [{"type": "Feature", "geometry": {"type": "Point", "coordinates": [-84.5137495, 39.100142800000015]}, "properties": {"dc_title_s": "M.E. Kuhn: Umbrellas, Parasols, Walking Canes", "ark": "fk4c53x39v", "id": "10319", "Geometry Type": "Point", "Location": "Cincinnati, OH", "Year": "null", "Language": "eng", "Street Address (If Available)": "62 West Fourth Street, Cincinnati, Oh", "Subject Terms": "Umbrella Industry|Advertising Cards|Jewish Merchants|Jewish Peddlers|Staffs (sticks, Canes, Etc.)"}}]}