{"type": "FeatureCollection", "features": [{"type": "Feature", "geometry": {"type": "Point", "coordinates": [-76.14558779999999, 43.0362102]}, "properties": {"dc_title_s": "I.M. Liberman: Dress & Fancy Goods", "ark": "fk4c256q3q", "id": "9250", "Geometry Type": "Point", "Location": "Syracuse, NY", "Year": "null", "Language": "eng", "Street Address (If Available)": "103 Grape Street, Syracuse, Ny", "Subject Terms": "Notions (merchandise)|Advertising Cards|Jewish Merchants|Jewish Peddlers|Dry-goods|Stores, Retail|Dressmaking Materials"}}]}