{"type": "FeatureCollection", "features": [{"type": "Feature", "geometry": {"type": "Point", "coordinates": [-76.99024559999998, 43.06423050000002]}, "properties": {"dc_title_s": "Hoffman & Robinson: Jewelers", "ark": "fk4cc19v9v", "id": "8144", "Geometry Type": "Point", "Location": "Lyons, NY", "Year": "null", "Language": "eng", "Street Address (If Available)": "Lyons, Ny", "Subject Terms": "Jewelers|Advertising Cards|Jewish Merchants|Jewish Peddlers"}}]}