{"type": "FeatureCollection", "features": [{"type": "Feature", "geometry": {"type": "Point", "coordinates": [-73.99800899999997, 40.745952]}, "properties": {"dc_title_s": "Erich's: Children's Mother Hubbard Dresses", "ark": "fk4c53x327", "id": "7848", "Geometry Type": "Point", "Location": "New York, NY", "Year": "null", "Language": "eng", "Street Address (If Available)": "8th Avenue And 24th Street, New York, Ny", "Subject Terms": "Clothing Trade|Advertising Cards|Jewish Merchants|Jewish Peddlers|Children's Clothing Industry"}}]}