{"type": "FeatureCollection", "features": [{"type": "Feature", "geometry": {"type": "Point", "coordinates": [-73.9929992, 40.72396240000002]}, "properties": {"dc_title_s": "W. Jacobs: Fine Boots And Shoes", "ark": "fk4cg0185q", "id": "9119", "Geometry Type": "Point", "Location": "New York, NY", "Year": "null", "Language": "eng", "Street Address (If Available)": "282 Bowery, New York, Ny", "Subject Terms": "Shoe Industry|Advertising Cards|Jewish Merchants|Jewish Peddlers|Boots"}}]}