{"type": "FeatureCollection", "features": [{"type": "Feature", "geometry": {"type": "Point", "coordinates": [-90.0645353, 29.950667100000018]}, "properties": {"dc_title_s": "A. Shwartz & Son: Dry Goods", "ark": "fk4cv4ts95", "id": "12796", "Geometry Type": "Point", "Location": "New Orleans, LA", "Year": "null", "Language": "eng", "Street Address (If Available)": "133 Canal Street, New Orleans, La", "Subject Terms": "Dry-goods|Advertising Cards|Jewish Merchants|Jewish Peddlers|Stores, Retail"}}]}