{"type": "FeatureCollection", "features": [{"type": "Feature", "geometry": {"type": "Point", "coordinates": [-74.784707, 40.22804900000001]}, "properties": {"dc_title_s": "Greenwald's: Boot & Shoe Store", "ark": "fk4c82mg48", "id": "6036", "Geometry Type": "Point", "Location": "Trenton, NJ", "Year": "null", "Language": "eng", "Street Address (If Available)": "23 South Greene Street, Trenton, Nj", "Subject Terms": "Shoe Industry|Advertising Cards|Jewish Merchants|Jewish Peddlers|Boots|Stores, Retail|Shoe Store"}}]}