{"type": "FeatureCollection", "features": [{"type": "Feature", "geometry": {"type": "Point", "coordinates": [-93.27055320000001, 44.97831510000002]}, "properties": {"dc_title_s": "Segelbaum Bro's.: Dry Goods, Millinery, Fancy Goods & Notions", "ark": "fk4cr64d82", "id": "13749", "Geometry Type": "Point", "Location": "Minneapolis, MN", "Year": "null", "Language": "eng", "Street Address (If Available)": "259 Nicollet Avenue, Minneapolis, Mn", "Subject Terms": "Dry-goods|Advertising Cards|Jewish Merchants|Jewish Peddlers|Stores, Retail|Notions (merchandise)|Millinery|Notions (merchandise)"}}]}