{"type": "FeatureCollection", "features": [{"type": "Feature", "geometry": {"type": "Point", "coordinates": [-75.1930077, 39.95449289999999]}, "properties": {"dc_title_s": "Mrs. Heinaman's: Boarding And Lodging House", "ark": "fk4d50z05w", "id": "3003", "Geometry Type": "Point", "Location": "Philadelphia, PA", "Year": "null", "Language": "eng", "Street Address (If Available)": "3437 Chestnut Street, Between 34th And 35th Streets, Philadelphia, Pa", "Subject Terms": "Boardinghouses|Advertising Cards|Jewish Merchants|Jewish Peddlers"}}]}