{"type": "FeatureCollection", "features": [{"type": "Feature", "geometry": {"type": "Point", "coordinates": [-82.445154, 38.4192496]}, "properties": {"dc_title_s": "M. Weil: Clothing & Gent's Furnishing Goods", "ark": "fk4dv1vp98", "id": "13131", "Geometry Type": "Point", "Location": "Huntington, WV", "Year": "1885", "Language": "eng", "Street Address (If Available)": "Huntington, Wv", "Subject Terms": "Clothing Trade|Advertising Cards|Jewish Merchants|Jewish Peddlers|Men's Furnishing Goods"}}]}