{"type": "FeatureCollection", "features": [{"type": "Feature", "geometry": {"type": "Point", "coordinates": [-73.99711499999998, 40.74748009999999]}, "properties": {"dc_title_s": "Jacob Geswein: Boot And Shoe Store", "ark": "fk4d79nc86", "id": "8994", "Geometry Type": "Point", "Location": "New York, NY", "Year": "null", "Language": "eng", "Street Address (If Available)": "325 Eighth Avenue, Between 26th And 27th Streets, New York, Ny", "Subject Terms": "Shoe Industry|Advertising Cards|Jewish Merchants|Jewish Peddlers|Boots|Stores, Retail|Shoe Store"}}]}