{"type": "FeatureCollection", "features": [{"type": "Feature", "geometry": {"type": "Point", "coordinates": [-74.0059728, 40.712775300000004]}, "properties": {"dc_title_s": "Herman Loeb: Armant's Perfumes", "ark": "fk4fj2sf58", "id": "8374", "Geometry Type": "Point", "Location": "New York, NY", "Year": "null", "Language": "eng", "Street Address (If Available)": "New York, Ny", "Subject Terms": "Perfumes Industry|Advertising Cards|Jewish Merchants|Jewish Peddlers"}}]}