{"type": "FeatureCollection", "features": [{"type": "Feature", "geometry": {"type": "Point", "coordinates": [-87.62448969999998, 41.88211150000001]}, "properties": {"dc_title_s": "L. Hirschberg & Co's: The Diamond Palace: Jewelry Store", "ark": "fk4fx7m03z", "id": "12047", "Geometry Type": "Point", "Location": "Chicago, IL", "Year": "null", "Language": "eng", "Street Address (If Available)": "119 East Madison Street, Chicago, Il", "Subject Terms": "Diamond Industry And Trade|Advertising Cards|Jewish Merchants|Jewish Peddlers|Jewelers|Stores, Retail"}}]}