{"type": "FeatureCollection", "features": [{"type": "Feature", "geometry": {"type": "Point", "coordinates": [-73.9827607, 40.73838760000004]}, "properties": {"dc_title_s": "Stern Brothers: Fine Shoes Of All Kinds", "ark": "fk4f198h04", "id": "6977", "Geometry Type": "Point", "Location": "New York, NY", "Year": "null", "Language": "eng", "Street Address (If Available)": "32, 34, & 36 West 23rd Street, Manhattan, Ny", "Subject Terms": "Shoe Industry|Advertising Cards|Jewish Merchants|Jewish Peddlers"}}]}