{"type": "FeatureCollection", "features": [{"type": "Feature", "geometry": {"type": "Point", "coordinates": [-73.98328990000002, 40.74201649999999]}, "properties": {"dc_title_s": "S. Salomon: Millinery, Kid Gloves, Neckwear", "ark": "fk4f76p87s", "id": "6806", "Geometry Type": "Point", "Location": "New York, NY", "Year": "null", "Language": "eng", "Street Address (If Available)": "92 Lexington Street, Manhattan, Ny", "Subject Terms": "Millinery|Advertising Cards|Jewish Merchants|Jewish Peddlers|Glove Industry|Neckwear|Children's Clothing Industry"}}]}