{"type": "FeatureCollection", "features": [{"type": "Feature", "geometry": {"type": "Point", "coordinates": [-73.75242600000001, 42.6502031]}, "properties": {"dc_title_s": "Daniel Bachrach: Fancy Goods", "ark": "fk4fr0672n", "id": "7096", "Geometry Type": "Point", "Location": "Albany, NY", "Year": "null", "Language": "eng", "Street Address (If Available)": "13 North Pearl Street, Albany, Ny", "Subject Terms": "Notions (merchandise)|Advertising Cards|Jewish Merchants|Jewish Peddlers|Dry-goods|Stores, Retail"}}]}