{"type": "FeatureCollection", "features": [{"type": "Feature", "geometry": {"type": "Point", "coordinates": [-81.6924655, 41.500249600000004]}, "properties": {"dc_title_s": "Steinfeld: Clothier, Tailor & Furnisher", "ark": "fk4gf13z8w", "id": "10383", "Geometry Type": "Point", "Location": "Cleveland, OH", "Year": "null", "Language": "eng", "Street Address (If Available)": "242 & 244 Superior Avenue, Cleveland, Oh", "Subject Terms": "Clothing Trade|Advertising Cards|Jewish Merchants|Jewish Peddlers|Tailoring|House Furnishings Industry And Trade|Stores, Retail"}}]}