{"type": "FeatureCollection", "features": [{"type": "Feature", "geometry": {"type": "Point", "coordinates": [-73.75284820000002, 42.6488834]}, "properties": {"dc_title_s": "C.L. Swartz: Boot And Shoe Store", "ark": "fk4gt5xh7p", "id": "7089", "Geometry Type": "Point", "Location": "Albany, NY", "Year": "null", "Language": "eng", "Street Address (If Available)": "12 South Pearl Street, Opposite The Globe Hotel, Albany, Ny", "Subject Terms": "Shoe Industry|Advertising Cards|Jewish Merchants|Jewish Peddlers|Boots|Stores, Retail|Shoe Store"}}]}