{"type": "FeatureCollection", "features": [{"type": "Feature", "geometry": {"type": "Point", "coordinates": [-76.80773379999998, 42.089796500000006]}, "properties": {"dc_title_s": "Benjamin's: Fine Candies And Imported Fruits", "ark": "fk4hd84v56", "id": "8706", "Geometry Type": "Point", "Location": "Elmira, NY", "Year": "1885", "Language": "eng", "Street Address (If Available)": "Elmira, Ny", "Subject Terms": "Imports|Advertising Cards|Jewish Merchants|Jewish Peddlers|Fruit Trade|Produce Trade|Candy Industry"}}]}