{"type": "FeatureCollection", "features": [{"type": "Feature", "geometry": {"type": "Point", "coordinates": [-87.6291529, 41.881884299999996]}, "properties": {"dc_title_s": "Mcvicker's Theatre: 'that's My Regular Business', The Great German-american Dialect Actor, Mr. Max Fehrmann, In The Great Hebrew Play Of Uncle Isaac!, Wednesday & Saturday Matinees. J. H. Meade, Manager.", "ark": "fk4hm5jm36", "id": "13318", "Geometry Type": "Point", "Location": "Chicago, IL", "Year": "null", "Language": "eng", "Street Address (If Available)": "Mcvicker's Theatre, Chicago, Il", "Subject Terms": "Theater|Advertising Cards|Jewish Merchants|Jewish Peddlers|Mcvicker's Theatre|Actors|Bible Plays, Hebrew"}}]}