{"type": "FeatureCollection", "features": [{"type": "Feature", "geometry": {"type": "Point", "coordinates": [-76.1328051, 43.0522505]}, "properties": {"dc_title_s": "Schwarz Bro.'s: Easter Presents", "ark": "fk4hm5jn04", "id": "9330", "Geometry Type": "Point", "Location": "Syracuse, NY", "Year": "null", "Language": "eng", "Street Address (If Available)": "218, 220 Lodi Street, Syracuse, Ny", "Subject Terms": "Easter|Advertising Cards|Jewish Merchants|Jewish Peddlers|Gift Shops"}}]}