{"type": "FeatureCollection", "features": [{"type": "Feature", "geometry": {"type": "Point", "coordinates": [-76.14742439999999, 43.0481221]}, "properties": {"dc_title_s": "S. Rosenbloom & Sons: Boot And Shoe Dealers", "ark": "fk4hm5jn25", "id": "10178", "Geometry Type": "Point", "Location": "Syracuse, NY", "Year": "null", "Language": "eng", "Street Address (If Available)": "Syracuse, Ny", "Subject Terms": "Shoe Industry|Advertising Cards|Jewish Merchants|Jewish Peddlers|Boots"}}]}