{"type": "FeatureCollection", "features": [{"type": "Feature", "geometry": {"type": "Point", "coordinates": [-73.98864059999997, 40.691683900000015]}, "properties": {"dc_title_s": "Schlang Bros.: Clothing", "ark": "fk4hm5jm8s", "id": "799", "Geometry Type": "Point", "Location": "Brooklyn, NY", "Year": "null", "Language": "eng", "Street Address (If Available)": "218 & 220 Fulton Street, Brooklyn, Ny", "Subject Terms": "Clothing Trade|Advertising Cards|Jewish Merchants|Jewish Peddlers|Stores, Retail"}}]}