{"type": "FeatureCollection", "features": [{"type": "Feature", "geometry": {"type": "Point", "coordinates": [-74.0067557, 40.713624800000005]}, "properties": {"dc_title_s": "Siegel's: Extra Dry Champagne And Wine Vaults (l. Siegel)", "ark": "fk4h99ff88", "id": "6751", "Geometry Type": "Point", "Location": "New York, NY", "Year": "null", "Language": "eng", "Street Address (If Available)": "Corner Warren And Broadway, Manhattan, Ny", "Subject Terms": "Dry-goods|Advertising Cards|Jewish Merchants|Jewish Peddlers|Stores, Retail|Wine Industry|Alcoholic Beverage Industry|Sparkling Wines Industry"}}]}