{"type": "FeatureCollection", "features": [{"type": "Feature", "geometry": {"type": "Point", "coordinates": [-75.14240320000002, 39.95614820000003]}, "properties": {"dc_title_s": "David Seidmann: Manufacturer Of Upholstery Fringes", "ark": "fk4hm5jn1n", "id": "2905", "Geometry Type": "Point", "Location": "Philadelphia, PA", "Year": "null", "Language": "eng", "Street Address (If Available)": "323 North Second Street, Philadelphia, Pa", "Subject Terms": "Manufactures|Advertising Cards|Jewish Merchants|Jewish Peddlers|Textile Industry"}}]}