{"type": "FeatureCollection", "features": [{"type": "Feature", "geometry": {"type": "Point", "coordinates": [-89.1764608, 37.005329300000014]}, "properties": {"dc_title_s": "Samuel Burger: Palace Clothier", "ark": "fk4hx1nr9b", "id": "11976", "Geometry Type": "Point", "Location": "Cairo, IL", "Year": "null", "Language": "eng", "Street Address (If Available)": "Cairo, Il", "Subject Terms": "Clothing Trade|Advertising Cards|Jewish Merchants|Jewish Peddlers|Stores, Retail"}}]}