{"type": "FeatureCollection", "features": [{"type": "Feature", "geometry": {"type": "Point", "coordinates": [-74.1734597, 40.91724910000001]}, "properties": {"dc_title_s": "B. Rubenstein: Jeweler", "ark": "fk4h421p3w", "id": "5949", "Geometry Type": "Point", "Location": "Paterson, NJ", "Year": "null", "Language": "eng", "Street Address (If Available)": "206 Main Street, Paterson, Nj", "Subject Terms": "Jewelers|Advertising Cards|Jewish Merchants|Jewish Peddlers"}}]}