{"type": "FeatureCollection", "features": [{"type": "Feature", "geometry": {"type": "Point", "coordinates": [-78.87836889999998, 42.8864468]}, "properties": {"dc_title_s": "Rosenbloom Bros.: Manufacturers And Retailers Of Boots And Shoes (syracuse, Auburn, Buffalo)", "ark": "fk4h99fg0m", "id": "890", "Geometry Type": "Point", "Location": "Buffalo, NY", "Year": "null", "Language": "eng", "Street Address (If Available)": "Buffalo, Ny", "Subject Terms": "Dealers (retail Trade)|Advertising Cards|Jewish Merchants|Jewish Peddlers|Manufactures|Shoe Industry|Boots|Stores, Retail|Shoe Store"}}]}