{"type": "FeatureCollection", "features": [{"type": "Feature", "geometry": {"type": "Point", "coordinates": [-78.38687669999999, 43.21977849999999]}, "properties": {"dc_title_s": "J.N. Kersburg: Dry Goods, Carpets & Clothing", "ark": "fk4h421p6f", "id": "8175", "Geometry Type": "Point", "Location": "Medina, NY", "Year": "null", "Language": "eng", "Street Address (If Available)": "54 & 60 Main Street, Medina, Ny", "Subject Terms": "Dry-goods|Advertising Cards|Jewish Merchants|Jewish Peddlers|Stores, Retail|Rug And Carpet Industry|Clothing Trade"}}]}