{"type": "FeatureCollection", "features": [{"type": "Feature", "geometry": {"type": "Point", "coordinates": [-73.9968432, 40.737368000000004]}, "properties": {"dc_title_s": "Rothenberg's: Certificate For Free Portrait", "ark": "fk4h70r24f", "id": "6732", "Geometry Type": "Point", "Location": "New York, NY", "Year": "null", "Language": "eng", "Street Address (If Available)": "14th Street & 6th Avenue , Manhattan, Ny", "Subject Terms": "Advertising Cards|Jewish Merchants|Jewish Peddlers"}}]}