{"type": "FeatureCollection", "features": [{"type": "Feature", "geometry": {"type": "Point", "coordinates": [-87.64689290000001, 41.87927490000003]}, "properties": {"dc_title_s": "Newberger & Jacobsohn: Merchant Tailors", "ark": "fk4j10c55j", "id": "12133", "Geometry Type": "Point", "Location": "Chicago, IL", "Year": "null", "Language": "eng", "Street Address (If Available)": "191 South Halsted Street, Near Van Buren Street, Chicago, Il", "Subject Terms": "Clothing Trade|Advertising Cards|Jewish Merchants|Jewish Peddlers|Textile Industry|Tailoring"}}]}