{"type": "FeatureCollection", "features": [{"type": "Feature", "geometry": {"type": "Point", "coordinates": [-73.7528796, 42.648844100000005]}, "properties": {"dc_title_s": "Mandelbaum: Ladies' Fine Shoes, Misses' Solid Shoes, Children's Spring Heel", "ark": "fk4jh3w44t", "id": "7220", "Geometry Type": "Point", "Location": "Albany, NY", "Year": "null", "Language": "eng", "Street Address (If Available)": "20 South Pearl Street, Albany, Ny", "Subject Terms": "Shoe Industry|Advertising Cards|Jewish Merchants|Jewish Peddlers|Children's Shoe Industry"}}]}