{"type": "FeatureCollection", "features": [{"type": "Feature", "geometry": {"type": "Point", "coordinates": [-73.9928, 40.703789]}, "properties": {"dc_title_s": "Al Kaufman, Leach Cross, Boxer, From Mecca & Hassan Cigarettes Champion Athlete And Prize Fighter Collection, 1910", "ark": "fk4j10c57k", "id": "256", "Geometry Type": "Point", "Location": "Brooklyn, NY", "Year": "1910", "Language": "eng", "Street Address (If Available)": "New York, Ny", "Subject Terms": "Cigarette Industry|Advertising Cards|Jewish Merchants|Jewish Peddlers|Tobacco Industry"}}]}