{"type": "FeatureCollection", "features": [{"type": "Feature", "geometry": {"type": "Point", "coordinates": [-74.00882899999999, 40.7096016]}, "properties": {"dc_title_s": "Starr & Marcus: Diamonds, Jewelry, & Sterling Silveware", "ark": "fk4jw8pp7n", "id": "6465", "Geometry Type": "Point", "Location": "New York, NY", "Year": "null", "Language": "eng", "Street Address (If Available)": "22 John Street, Manhattan, Ny", "Subject Terms": "Diamond Industry And Trade|Advertising Cards|Jewish Merchants|Jewish Peddlers|Jewelers|Silverware"}}]}