{"type": "FeatureCollection", "features": [{"type": "Feature", "geometry": {"type": "Point", "coordinates": [-73.94070830000001, 40.80210920000002]}, "properties": {"dc_title_s": "F.A. Reeves: Millinery And Fancy Goods", "ark": "fk4j10c59m", "id": "6178", "Geometry Type": "Point", "Location": "New York, NY", "Year": "null", "Language": "eng", "Street Address (If Available)": "1729 Ridge Avenue, Manhattan, Ny", "Subject Terms": "Millinery|Advertising Cards|Jewish Merchants|Jewish Peddlers|Notions (merchandise)|Dry-goods|Millinery|Stores, Retail"}}]}