{"type": "FeatureCollection", "features": [{"type": "Feature", "geometry": {"type": "Point", "coordinates": [-73.9933534, 40.72106769999999]}, "properties": {"dc_title_s": "M. Benjamin's: Dining Room", "ark": "fk4kk9md98", "id": "8005", "Geometry Type": "Point", "Location": "New York, NY", "Year": "1881", "Language": "eng", "Street Address (If Available)": "199 Bowery, Opposite Spring Street, New York, Ny", "Subject Terms": "Restaurateurs|Advertising Cards|Jewish Merchants|Jewish Peddlers"}}]}