{"type": "FeatureCollection", "features": [{"type": "Feature", "geometry": {"type": "Point", "coordinates": [-81.68996389999998, 41.49643019999999]}, "properties": {"dc_title_s": "C.H. Seymour: Furniture And Carpets", "ark": "fk4k64sw2d", "id": "10346", "Geometry Type": "Point", "Location": "Cleveland, OH", "Year": "null", "Language": "eng", "Street Address (If Available)": "161 Ontario Street, Cleveland, Oh", "Subject Terms": "Rug And Carpet Industry|Advertising Cards|Jewish Merchants|Jewish Peddlers|Furniture Industry And Trade"}}]}