{"type": "FeatureCollection", "features": [{"type": "Feature", "geometry": {"type": "Point", "coordinates": [-74.0064325, 40.70985670000002]}, "properties": {"dc_title_s": "Berman Fish Co.", "ark": "fk4kh0x12w", "id": "6136", "Geometry Type": "Point", "Location": "New York, NY", "Year": "null", "Language": "eng", "Street Address (If Available)": "109 Fulton Market, Manhattan, Ny", "Subject Terms": "Fish Trade|Advertising Cards|Jewish Merchants|Jewish Peddlers"}}]}