{"type": "FeatureCollection", "features": [{"type": "Feature", "geometry": {"type": "Point", "coordinates": [-76.14742439999999, 43.0481221]}, "properties": {"dc_title_s": "N.L. Rosenthal's: Dry Goods, Groceries, And House Furnishing Goods", "ark": "fk4kd26n4w", "id": "9318", "Geometry Type": "Point", "Location": "Syracuse, NY", "Year": "1882", "Language": "eng", "Street Address (If Available)": "Syracuse, Ny", "Subject Terms": "Dry-goods|Advertising Cards|Jewish Merchants|Jewish Peddlers|Stores, Retail|Grocer|House Furnishings Industry And Trade"}}]}