{"type": "FeatureCollection", "features": [{"type": "Feature", "geometry": {"type": "Point", "coordinates": [-76.5505769, 40.78242079999998]}, "properties": {"dc_title_s": "F. Israel Bros.: Keystone Shoe Store", "ark": "fk4kh0x13d", "id": "2337", "Geometry Type": "Point", "Location": "Shamokin, PA", "Year": "null", "Language": "eng", "Street Address (If Available)": "Shamokin Street, Shamokin, Pa", "Subject Terms": "Shoe Industry|Advertising Cards|Jewish Merchants|Jewish Peddlers|Stores, Retail|Shoe Store"}}]}