{"type": "FeatureCollection", "features": [{"type": "Feature", "geometry": {"type": "Point", "coordinates": [-70.8740841, 42.8121448]}, "properties": {"dc_title_s": "Hart Bros: Provisions", "ark": "fk4ks7159q", "id": "13500", "Geometry Type": "Point", "Location": "Newburyport, MA", "Year": "null", "Language": "eng", "Street Address (If Available)": "79 & 81 Merrimac Street, Newburyport, Ma", "Subject Terms": "Grocers|Advertising Cards|Jewish Merchants|Jewish Peddlers|Outfitting Industry"}}]}