{"type": "FeatureCollection", "features": [{"type": "Feature", "geometry": {"type": "Point", "coordinates": [-76.6060918, 39.294589000000016]}, "properties": {"dc_title_s": "S. Ulman: Fine Boots & Shoes", "ark": "fk4kp89s77", "id": "12990", "Geometry Type": "Point", "Location": "Baltimore, MD", "Year": "null", "Language": "eng", "Street Address (If Available)": "421 North Gay Street, Baltimore, Md", "Subject Terms": "Shoe Industry|Advertising Cards|Jewish Merchants|Jewish Peddlers|Shoe Store|Boots|Stores, Retail"}}]}