{"type": "FeatureCollection", "features": [{"type": "Feature", "geometry": {"type": "Point", "coordinates": [-74.00594689999998, 40.72086220000001]}, "properties": {"dc_title_s": "Kaldenberg & Son: Turners And Fancy Workers: Glazier Diamonds And Brilliant Points For Engravers: Manufacturers Of Meershaum Pipes", "ark": "fk4ms4234q", "id": "6307", "Geometry Type": "Point", "Location": "New York, NY", "Year": "null", "Language": "eng", "Street Address (If Available)": "6 John Street, Near Broadway, Manhattan, Ny", "Subject Terms": "Diamond Industry And Trade|Advertising Cards|Jewish Merchants|Jewish Peddlers|Tobacco Pipe Industry|Tobacco Industry|Engraver|Glaziers"}}]}