{"type": "FeatureCollection", "features": [{"type": "Feature", "geometry": {"type": "Point", "coordinates": [-87.62837900000001, 41.882017399999995]}, "properties": {"dc_title_s": "Rothschild, Goldsmith & Stein: Manufacturers And Jobbers Of Boots & Shoes", "ark": "fk4mc97h3r", "id": "12151", "Geometry Type": "Point", "Location": "Chicago, IL", "Year": "1881", "Language": "eng", "Street Address (If Available)": "14 & 16 Madison Street, Chicago, Il", "Subject Terms": "Distributors (commerce)|Advertising Cards|Jewish Merchants|Jewish Peddlers|Manufactures|Shoe Industry|Boots"}}]}