{"type": "FeatureCollection", "features": [{"type": "Feature", "geometry": {"type": "Point", "coordinates": [-84.52037809999999, 39.09920970000003]}, "properties": {"dc_title_s": "Loewenstein Canning Company: Compressed Corned Beef", "ark": "fk4m90j55h", "id": "10313", "Geometry Type": "Point", "Location": "Cincinnati, OH", "Year": "null", "Language": "eng", "Street Address (If Available)": "569-579 John Street, Cincinnati, Oh", "Subject Terms": "Corned Beef|Advertising Cards|Jewish Merchants|Jewish Peddlers|Canned Foods Industry|Beef Industry|Meat Industry And Trade"}}]}