{"type": "FeatureCollection", "features": [{"type": "Feature", "geometry": {"type": "Point", "coordinates": [-74.7610286, 40.2204311]}, "properties": {"dc_title_s": "Harry Levy: Manufacturer Of Fine Cigars", "ark": "fk4m61ts10", "id": "2663", "Geometry Type": "Point", "Location": "Trenton, NJ", "Year": "1882", "Language": "eng", "Street Address (If Available)": "214 East State Street, Trenton, Nj", "Subject Terms": "Cigar Industry|Advertising Cards|Jewish Merchants|Jewish Peddlers|Tobacco Industry|Manufactures|Cigar Industry"}}]}