{"type": "FeatureCollection", "features": [{"type": "Feature", "geometry": {"type": "Point", "coordinates": [-74.78476900000001, 40.22798800000001]}, "properties": {"dc_title_s": "Simon Samler: Clothier", "ark": "fk4ms42336", "id": "6048", "Geometry Type": "Point", "Location": "Trenton, NJ", "Year": "null", "Language": "eng", "Street Address (If Available)": "27 South Greene Street, Trenton, Nj", "Subject Terms": "Clothing Trade|Advertising Cards|Jewish Merchants|Jewish Peddlers|Stores, Retail"}}]}