{"type": "FeatureCollection", "features": [{"type": "Feature", "geometry": {"type": "Point", "coordinates": [-74.00605910000002, 40.706428700000004]}, "properties": {"dc_title_s": "Joseph S. Gans & Co.: Importers And Packers Of Leaf Tobacco (jos. S. Gans, Jerome Waller, Moses J. Gans, Edwin I. Alexaner)", "ark": "fk4m61tr5k", "id": "6277", "Geometry Type": "Point", "Location": "New York, NY", "Year": "null", "Language": "eng", "Street Address (If Available)": "150 Water Street, Manhattan, Ny", "Subject Terms": "Imports|Advertising Cards|Jewish Merchants|Jewish Peddlers|Tobacco Industry|Packing-houses"}}]}