{"type": "FeatureCollection", "features": [{"type": "Feature", "geometry": {"type": "Point", "coordinates": [-85.29084030000001, 42.64586820000001]}, "properties": {"dc_title_s": "Lewis Stern: Self-adjusting Corset", "ark": "fk4nz8gr5p", "id": "13659", "Geometry Type": "Point", "Location": "Hastings, NY", "Year": "null", "Language": "eng", "Street Address (If Available)": "Hastings, Mi", "Subject Terms": "Corset Industry|Advertising Cards|Jewish Merchants|Jewish Peddlers"}}]}