{"type": "FeatureCollection", "features": [{"type": "Feature", "geometry": {"type": "Point", "coordinates": [-75.22699379999999, 41.374215100000015]}, "properties": {"dc_title_s": "M. Lipsky: Ready Made Clothing", "ark": "fk4nk3p72b", "id": "9358", "Geometry Type": "Point", "Location": "Palmyra, NY", "Year": "1882", "Language": "eng", "Street Address (If Available)": "96 Andrew Street Bridge, Palmyra, Ny", "Subject Terms": "Clothing Trade|Advertising Cards|Jewish Merchants|Jewish Peddlers|Stores, Retail|Ready-to-wear Clothing Industry"}}]}