{"type": "FeatureCollection", "features": [{"type": "Feature", "geometry": {"type": "Point", "coordinates": [-94.5829695, 39.10503290000001]}, "properties": {"dc_title_s": "J.C. Altman & Bro.: Fine Shoes And Slippers", "ark": "fk4nz8gr24", "id": "12395", "Geometry Type": "Point", "Location": "Kansas City, MO", "Year": "null", "Language": "eng", "Street Address (If Available)": "707 Main Street, Kansas City, Mo", "Subject Terms": "Shoe Industry|Advertising Cards|Jewish Merchants|Jewish Peddlers|Slipper Industry"}}]}