{"type": "FeatureCollection", "features": [{"type": "Feature", "geometry": {"type": "Point", "coordinates": [-73.99108439999999, 40.74217180000001]}, "properties": {"dc_title_s": "Stern Brothers: Christmas Stocking, Gifts For Children, Gentlemen, And Ladies", "ark": "fk4ns1307c", "id": "6972", "Geometry Type": "Point", "Location": "New York, NY", "Year": "null", "Language": "eng", "Street Address (If Available)": "32, 34, 36 West 23rd Street, Manhattan, Ny", "Subject Terms": "Gift Shops|Advertising Cards|Jewish Merchants|Jewish Peddlers|Stores, Retail|Christmas"}}]}