{"type": "FeatureCollection", "features": [{"type": "Feature", "geometry": {"type": "Point", "coordinates": [-85.7443279, 38.25386990000001]}, "properties": {"dc_title_s": "J.N. Schlessinger: Shoes And Slippers", "ark": "fk4ng4zt1w", "id": "12380", "Geometry Type": "Point", "Location": "Louisville, KY", "Year": "null", "Language": "eng", "Street Address (If Available)": "453 East Market Street, Louisville, Ky", "Subject Terms": "Shoe Industry|Advertising Cards|Jewish Merchants|Jewish Peddlers|Slipper Industry"}}]}