{"type": "FeatureCollection", "features": [{"type": "Feature", "geometry": {"type": "Point", "coordinates": [-76.63377089999999, 39.28876070000001]}, "properties": {"dc_title_s": "N. Lowenthal: Fine Shoes", "ark": "fk4nz8gr3n", "id": "12949", "Geometry Type": "Point", "Location": "Baltimore, MD", "Year": "null", "Language": "eng", "Street Address (If Available)": "Corner Baltimore And Schroeder Streets, Baltimore, Md", "Subject Terms": "Shoe Industry|Advertising Cards|Jewish Merchants|Jewish Peddlers"}}]}