{"type": "FeatureCollection", "features": [{"type": "Feature", "geometry": {"type": "Point", "coordinates": [-74.00252940000001, 40.739743300000015]}, "properties": {"dc_title_s": "Jacobs & Bernstein's: Fine Shoes", "ark": "fk4ng4zt5z", "id": "7969", "Geometry Type": "Point", "Location": "New York, NY", "Year": "null", "Language": "eng", "Street Address (If Available)": "Corner Of 14th Street And Eighth Avenue, New York, Ny", "Subject Terms": "Shoe Industry|Advertising Cards|Jewish Merchants|Jewish Peddlers"}}]}