{"type": "FeatureCollection", "features": [{"type": "Feature", "geometry": {"type": "Point", "coordinates": [-73.93519989999999, 40.74687820000001]}, "properties": {"dc_title_s": "Edelstein Bros.: Pawn Brokers", "ark": "fk4n87k15w", "id": "6167", "Geometry Type": "Point", "Location": "Long Island City, NY", "Year": "null", "Language": "eng", "Street Address (If Available)": "28-13 Jackson Avenue, Queens Plaza, Long Island City, Ny", "Subject Terms": "Pawnbroking|Advertising Cards|Jewish Merchants|Jewish Peddlers"}}]}