{"type": "FeatureCollection", "features": [{"type": "Feature", "geometry": {"type": "Point", "coordinates": [-71.4128343, 41.823989100000006]}, "properties": {"dc_title_s": "William Loeb & Co.: Rings", "ark": "fk4nv9sc1m", "id": "12714", "Geometry Type": "Point", "Location": "Providence, RI", "Year": "null", "Language": "eng", "Street Address (If Available)": "Providence, Ri", "Subject Terms": "Rings|Advertising Cards|Jewish Merchants|Jewish Peddlers|Jewelers"}}]}