{"type": "FeatureCollection", "features": [{"type": "Feature", "geometry": {"type": "Point", "coordinates": [-87.61605050000001, 41.8910743]}, "properties": {"dc_title_s": "Clark & Wise: Wise's Axle Grease", "ark": "fk4ns13018", "id": "11989", "Geometry Type": "Point", "Location": "Chicago, IL", "Year": "1881", "Language": "eng", "Street Address (If Available)": "385 Illinois Street, Chicago, Il", "Subject Terms": "Oils And Fats|Advertising Cards|Jewish Merchants|Jewish Peddlers|Axles"}}]}