{"type": "FeatureCollection", "features": [{"type": "Feature", "geometry": {"type": "Point", "coordinates": [-74.4425154, 40.49631049999998]}, "properties": {"dc_title_s": "Oscar Solomon: Millinery And Fancy Goods", "ark": "fk4pk0q35h", "id": "5671", "Geometry Type": "Point", "Location": "New Brunswick, NJ", "Year": "null", "Language": "eng", "Street Address (If Available)": "9 Church Street, New Brunswick, Nj", "Subject Terms": "Millinery|Advertising Cards|Jewish Merchants|Jewish Peddlers|Notions (merchandise)|Dry-goods|Millinery|Stores, Retail"}}]}