{"type": "FeatureCollection", "features": [{"type": "Feature", "geometry": {"type": "Point", "coordinates": [-71.41077489999998, 41.83347890000002]}, "properties": {"dc_title_s": "Jacob Finklestein: Dry & Fancy Goods", "ark": "fk4pv6t806", "id": "12663", "Geometry Type": "Point", "Location": "Providence, RI", "Year": "null", "Language": "eng", "Street Address (If Available)": "370 North Main Street, Providence, Ri", "Subject Terms": "Dry-goods|Advertising Cards|Jewish Merchants|Jewish Peddlers|Stores, Retail|Notions (merchandise)"}}]}