{"type": "FeatureCollection", "features": [{"type": "Feature", "geometry": {"type": "Point", "coordinates": [-76.61932689999999, 39.28956710000003]}, "properties": {"dc_title_s": "M. Wolfsheimer: Schenthal And Grunebaum, Gents' Furnishing Goods", "ark": "fk4pk0q32z", "id": "12937", "Geometry Type": "Point", "Location": "Baltimore, MD", "Year": "null", "Language": "eng", "Street Address (If Available)": "270 West Baltimore Street, Baltimore, Md", "Subject Terms": "Men's Furnishing Goods|Advertising Cards|Jewish Merchants|Jewish Peddlers"}}]}