{"type": "FeatureCollection", "features": [{"type": "Feature", "geometry": {"type": "Point", "coordinates": [-73.24538239999998, 42.4500845]}, "properties": {"dc_title_s": "Rosenfeld's: One Price Clothing House", "ark": "fk4pk0q33g", "id": "13519", "Geometry Type": "Point", "Location": "Pittsfield, MA", "Year": "null", "Language": "eng", "Street Address (If Available)": "Pittsfield, Ma", "Subject Terms": "Clothing Trade|Advertising Cards|Jewish Merchants|Jewish Peddlers|Stores, Retail"}}]}