{"type": "FeatureCollection", "features": [{"type": "Feature", "geometry": {"type": "Point", "coordinates": [-74.34846299999998, 43.046111800000006]}, "properties": {"dc_title_s": "I. Schwarz: Millinery, Fancy Goods And Notions", "ark": "fk4qn6fd4b", "id": "8825", "Geometry Type": "Point", "Location": "Gloversville, NY", "Year": "null", "Language": "eng", "Street Address (If Available)": "141 Main Street, Gloversville, Ny", "Subject Terms": "Millinery|Advertising Cards|Jewish Merchants|Jewish Peddlers|Notions (merchandise)|Notions (merchandise)|Dry-goods|Stores, Retail"}}]}