{"type": "FeatureCollection", "features": [{"type": "Feature", "geometry": {"type": "Point", "coordinates": [-73.99601820000001, 40.72672230000002]}, "properties": {"dc_title_s": "Lansdorf & Co.: Suits And Overcoats", "ark": "fk4qj7r108", "id": "9025", "Geometry Type": "Point", "Location": "New York, NY", "Year": "null", "Language": "eng", "Street Address (If Available)": "643 Broadway, Corner Bleecker Street, New York, Ny", "Subject Terms": "Cloaks|Advertising Cards|Jewish Merchants|Jewish Peddlers|Suits (clothing)|Clothing Trade"}}]}