{"type": "FeatureCollection", "features": [{"type": "Feature", "geometry": {"type": "Point", "coordinates": [-74.0002088, 40.71070540000001]}, "properties": {"dc_title_s": "Schall & Co.: Wholesale Manufacturers & Importers Of Confectioners' Ornaments & Materials (martin Keppler, Mina Schall)", "ark": "fk4q81mt86", "id": "6442", "Geometry Type": "Point", "Location": "New York, NY", "Year": "null", "Language": "eng", "Street Address (If Available)": "388 Pearl Street, Manhattan, Ny", "Subject Terms": "Distributors (commerce)|Advertising Cards|Jewish Merchants|Jewish Peddlers|Manufactures|Confectionery"}}]}