{"type": "FeatureCollection", "features": [{"type": "Feature", "geometry": {"type": "Point", "coordinates": [-87.65732889999998, 41.84220360000002]}, "properties": {"dc_title_s": "Loeb & Co.: Boots And Shoes", "ark": "fk4q52xd8q", "id": "12050", "Geometry Type": "Point", "Location": "Chicago, IL", "Year": "null", "Language": "eng", "Street Address (If Available)": "2886 Archer Avenue, Chicago, Il", "Subject Terms": "Shoe Industry|Advertising Cards|Jewish Merchants|Jewish Peddlers|Boots"}}]}