{"type": "FeatureCollection", "features": [{"type": "Feature", "geometry": {"type": "Point", "coordinates": [-73.97913399999999, 40.72045800000002]}, "properties": {"dc_title_s": "B. Arfmann: Wines, Liquors & Cordials", "ark": "fk4q81mt9q", "id": "7727", "Geometry Type": "Point", "Location": "New York, NY", "Year": "null", "Language": "eng", "Street Address (If Available)": "302 Second Street, New York, Ny", "Subject Terms": "Alcoholic Beverage Industry|Advertising Cards|Jewish Merchants|Jewish Peddlers|Liquor Industry|Wine Industry|Liqueurs"}}]}