{"type": "FeatureCollection", "features": [{"type": "Feature", "geometry": {"type": "Point", "coordinates": [-69.9667068, 43.9038566]}, "properties": {"dc_title_s": "D. Rosen: Second-hand Clothing, Boots, Shoes And Furniture", "ark": "fk4q81mv4m", "id": "2471", "Geometry Type": "Point", "Location": "Brunswick, ME", "Year": "null", "Language": "eng", "Street Address (If Available)": "186 1/2 Maine Street, Brunswick, Me", "Subject Terms": "Secondhand Trade|Advertising Cards|Jewish Merchants|Jewish Peddlers|Shoe Industry|Boots|Clothing Trade|Used Furniture Industry|Used Clothing Industry|Furniture Industry And Trade"}}]}