{"type": "FeatureCollection", "features": [{"type": "Feature", "geometry": {"type": "Point", "coordinates": [-76.661462, 42.542456000000016]}, "properties": {"dc_title_s": "M.S. Feinberg: Fine Watches, Clocks And Jewelry", "ark": "fk4qn6fd6c", "id": "9794", "Geometry Type": "Point", "Location": "Trumansburg, NY", "Year": "null", "Language": "eng", "Street Address (If Available)": "Page Block, Trumansburg, Ny", "Subject Terms": "Clock And Watch Makers|Advertising Cards|Jewish Merchants|Jewish Peddlers|Jewelers"}}]}