{"type": "FeatureCollection", "features": [{"type": "Feature", "geometry": {"type": "Point", "coordinates": [-73.9712488, 40.7830603]}, "properties": {"dc_title_s": "Rosenberg's: Merchant For Elastica Trademark Finishes (finishes For Buildings, Boats, And Doors)", "ark": "fk4qn6fd29", "id": "6718", "Geometry Type": "Point", "Location": "New York, NY", "Year": "null", "Language": "eng", "Street Address (If Available)": "Manhattan, Ny", "Subject Terms": "Finishes And Finishing|Advertising Cards|Jewish Merchants|Jewish Peddlers|Merchant"}}]}