{"type": "FeatureCollection", "features": [{"type": "Feature", "geometry": {"type": "Point", "coordinates": [-89.59051759999998, 40.69233059999999]}, "properties": {"dc_title_s": "S.B. Hartz & Co.: Hatters And Furriers", "ark": "fk4qj7r019", "id": "12275", "Geometry Type": "Point", "Location": "Peoria, IL", "Year": "null", "Language": "eng", "Street Address (If Available)": "323-325 Main Street, Peoria, Il", "Subject Terms": "Fur Trade|Advertising Cards|Jewish Merchants|Jewish Peddlers|Hat Trade"}}]}