{"type": "FeatureCollection", "features": [{"type": "Feature", "geometry": {"type": "Point", "coordinates": [-73.99111769999999, 40.76100149999999]}, "properties": {"dc_title_s": "Jos. Stiner & Co.: Importers, Teas And Coffees", "ark": "fk4r78nr1x", "id": "6854", "Geometry Type": "Point", "Location": "New York, NY", "Year": "null", "Language": "eng", "Street Address (If Available)": "663 Ninth Avenue, Manhattan, Ny", "Subject Terms": "Imports|Advertising Cards|Jewish Merchants|Jewish Peddlers|Coffee Industry|Tea Trade"}}]}