{"type": "FeatureCollection", "features": [{"type": "Feature", "geometry": {"type": "Point", "coordinates": [-73.99620029999997, 40.748433500000004]}, "properties": {"dc_title_s": "A.L. Isaacs: Florist", "ark": "fk4rr25p4f", "id": "8899", "Geometry Type": "Point", "Location": "New York, NY", "Year": "null", "Language": "eng", "Street Address (If Available)": "Corner Of 28th Street & 8th Avenue, New York, Ny", "Subject Terms": "Florists|Advertising Cards|Jewish Merchants|Jewish Peddlers"}}]}