{"type": "FeatureCollection", "features": [{"type": "Feature", "geometry": {"type": "Point", "coordinates": [-78.87503239999998, 42.885079000000005]}, "properties": {"dc_title_s": "L. Garson & Co.: Clothing, Merchants For J.W. Rosenthal Boys Clothing", "ark": "fk4rj4rx2z", "id": "859", "Geometry Type": "Point", "Location": "Buffalo, NY", "Year": "null", "Language": "eng", "Street Address (If Available)": "392 & 394 Main Street, Buffalo, Ny", "Subject Terms": "Clothing Trade|Advertising Cards|Jewish Merchants|Jewish Peddlers|Stores, Retail|Children's Clothing Industry"}}]}