{"type": "FeatureCollection", "features": [{"type": "Feature", "geometry": {"type": "Point", "coordinates": [-90.1542848, 41.44809020000001]}, "properties": {"dc_title_s": "P.S. Schnabele: Merchant Tailor, Clothier, Etc.", "ark": "fk4rb7c36g", "id": "12261", "Geometry Type": "Point", "Location": "Geneseo, IL", "Year": "null", "Language": "eng", "Street Address (If Available)": "Geneseo, Il", "Subject Terms": "Clothing Trade|Advertising Cards|Jewish Merchants|Jewish Peddlers|Textile Industry|Tailoring|Stores, Retail"}}]}