{"type": "FeatureCollection", "features": [{"type": "Feature", "geometry": {"type": "Point", "coordinates": [-70.8702845, 42.81031350000001]}, "properties": {"dc_title_s": "H. Feibelman: Boston Clothing Co.", "ark": "fk4rf62h0v", "id": "13291", "Geometry Type": "Point", "Location": "Newburyport, MA", "Year": "1883", "Language": "eng", "Street Address (If Available)": "40 State Street, Newburyport, Ma", "Subject Terms": "Clothing Trade|Advertising Cards|Jewish Merchants|Jewish Peddlers|Stores, Retail"}}]}