{"type": "FeatureCollection", "features": [{"type": "Feature", "geometry": {"type": "Point", "coordinates": [-77.0546903, 42.14285210000001]}, "properties": {"dc_title_s": "J. Saks: Jeweler", "ark": "fk4rx9kg15", "id": "8698", "Geometry Type": "Point", "Location": "Corning, NY", "Year": "null", "Language": "eng", "Street Address (If Available)": "Corning, Ny", "Subject Terms": "Jewelers|Advertising Cards|Jewish Merchants|Jewish Peddlers"}}]}