{"type": "FeatureCollection", "features": [{"type": "Feature", "geometry": {"type": "Point", "coordinates": [-75.14684310000001, 39.95011430000001]}, "properties": {"dc_title_s": "C. Oppenheimer, With Bloomingdale & Rhine: Wholesale Clothiers", "ark": "fk4rf62h9h", "id": "2902", "Geometry Type": "Point", "Location": "Philadelphia, PA", "Year": "null", "Language": "eng", "Street Address (If Available)": "332 Market Street, Below Fourth, Philadelphia, Pa", "Subject Terms": "Distributors (commerce)|Advertising Cards|Jewish Merchants|Jewish Peddlers|Clothing Trade|Stores, Retail"}}]}