{"type": "FeatureCollection", "features": [{"type": "Feature", "geometry": {"type": "Point", "coordinates": [-76.2614802, 42.103428699999995]}, "properties": {"dc_title_s": "Julius L. Straus': New York Bazaar", "ark": "fk4r217z25", "id": "8241", "Geometry Type": "Point", "Location": "Owego, NY", "Year": "null", "Language": "eng", "Street Address (If Available)": "41 Lake Street, Owego, Ny", "Subject Terms": "Department Stores|Advertising Cards|Jewish Merchants|Jewish Peddlers|Dry-goods|Notions (merchandise)|Clothing Trade|Textile Industry|Stores, Retail"}}]}