{"type": "FeatureCollection", "features": [{"type": "Feature", "geometry": {"type": "Point", "coordinates": [-93.26743099999999, 44.984678]}, "properties": {"dc_title_s": "L.E. Shoenberg: Boots & Shoes", "ark": "fk4r217z04", "id": "13714", "Geometry Type": "Point", "Location": "Minneapolis, MN", "Year": "null", "Language": "eng", "Street Address (If Available)": "28 First Street North, Minneapolis, Mn", "Subject Terms": "Shoe Industry|Advertising Cards|Jewish Merchants|Jewish Peddlers|Boots"}}]}