{"type": "FeatureCollection", "features": [{"type": "Feature", "geometry": {"type": "Point", "coordinates": [-73.93575190000001, 40.80430509999999]}, "properties": {"dc_title_s": "Goldsmid: Hatter", "ark": "fk4sx6mc18", "id": "8878", "Geometry Type": "Point", "Location": "Harlem, NY", "Year": "null", "Language": "eng", "Street Address (If Available)": "2312 Third Avenue, Between 125th And 126th Streets, Harlem, Ny", "Subject Terms": "Hat Trade|Advertising Cards|Jewish Merchants|Jewish Peddlers|Variety Stores|Clothing Trade|Silk Industry"}}]}