{"type": "FeatureCollection", "features": [{"type": "Feature", "geometry": {"type": "Point", "coordinates": [-73.9955236, 40.74936430000001]}, "properties": {"dc_title_s": "H. Lustberg: Furnishing Goods", "ark": "fk4s47085h", "id": "8388", "Geometry Type": "Point", "Location": "New York, NY", "Year": "1881", "Language": "eng", "Street Address (If Available)": "379 Eighth Avenue, Between Twenty Eighth & Twenty Ninth Streets , New York, Ny", "Subject Terms": "House Furnishings Industry And Trade|Advertising Cards|Jewish Merchants|Jewish Peddlers"}}]}