{"type": "FeatureCollection", "features": [{"type": "Feature", "geometry": {"type": "Point", "coordinates": [-75.1652215, 39.95258390000002]}, "properties": {"dc_title_s": "The Members Of The Philadelphia Stock Exchange: Request The Pleasure Of Mr. Moses A. Dropsie's Company", "ark": "fk4s75pn2j", "id": "3026", "Geometry Type": "Point", "Location": "Philadelphia, PA", "Year": "null", "Language": "eng", "Street Address (If Available)": "Philadelphia, Pa", "Subject Terms": "Philadelphia Stock Exchange|Advertising Cards|Jewish Merchants|Jewish Peddlers|Philadelphia Board Of Brokers|Dropsie, Moses A. (moses Aaron), 1821-1905"}}]}