{"type": "FeatureCollection", "features": [{"type": "Feature", "geometry": {"type": "Point", "coordinates": [-73.99455460000001, 40.718160900000015]}, "properties": {"dc_title_s": "S.W. Freund: Fancy Goods, Jewelry & Corsets", "ark": "fk4s47081f", "id": "9100", "Geometry Type": "Point", "Location": "New York, NY", "Year": "1881", "Language": "eng", "Street Address (If Available)": "241 Grand Street, New York, Ny", "Subject Terms": "Corset Industry|Advertising Cards|Jewish Merchants|Jewish Peddlers|Jewelers|Notions (merchandise)|Dry-goods|Stores, Retail"}}]}