{"type": "FeatureCollection", "features": [{"type": "Feature", "geometry": {"type": "Point", "coordinates": [-77.9442908, 34.23543020000001]}, "properties": {"dc_title_s": "M. Meyers: Clothier", "ark": "fk4s470730", "id": "12734", "Geometry Type": "Point", "Location": "Wilmington, DE", "Year": "null", "Language": "eng", "Street Address (If Available)": "406 Market Street, Wilmington, De", "Subject Terms": "Clothing Trade|Advertising Cards|Jewish Merchants|Jewish Peddlers|Stores, Retail"}}]}