{"type": "FeatureCollection", "features": [{"type": "Feature", "geometry": {"type": "Point", "coordinates": [-74.0059728, 40.712775300000004]}, "properties": {"dc_title_s": "Robert Griffin Morris: The Pulse Of New York (under The Management Of Gustave & Charles Frohman)", "ark": "fk4sb4d141", "id": "9082", "Geometry Type": "Point", "Location": "New York, NY", "Year": "null", "Language": "eng", "Street Address (If Available)": "New York, Ny", "Subject Terms": "Morris, Robert Griffin|Advertising Cards|Jewish Merchants|Jewish Peddlers|Frohman, Charles, 1860-1915|Frohman, Gustave, 1854-1930\r\n"}}]}