{"type": "FeatureCollection", "features": [{"type": "Feature", "geometry": {"type": "Point", "coordinates": [-87.62979819999998, 41.87811360000002]}, "properties": {"dc_title_s": "Selz, Schwab & Co.: Selz 'rock Bottom' Shoes", "ark": "fk4sn0h542", "id": "12184", "Geometry Type": "Point", "Location": "Chicago, IL", "Year": "null", "Language": "eng", "Street Address (If Available)": "Chicago, Il", "Subject Terms": "Shoe Industry|Advertising Cards|Jewish Merchants|Jewish Peddlers"}}]}