{"type": "FeatureCollection", "features": [{"type": "Feature", "geometry": {"type": "Point", "coordinates": [-76.6236198, 39.28509610000002]}, "properties": {"dc_title_s": "Wm. Reisinger & Son: Furniture", "ark": "fk4th8tp2f", "id": "12998", "Geometry Type": "Point", "Location": "Baltimore, MD", "Year": "null", "Language": "eng", "Street Address (If Available)": "49 Columbia Avenue, Baltimore, Md", "Subject Terms": "Furniture Industry And Trade|Advertising Cards|Jewish Merchants|Jewish Peddlers"}}]}