{"type": "FeatureCollection", "features": [{"type": "Feature", "geometry": {"type": "Point", "coordinates": [-77.0466037, 42.66258160000004]}, "properties": {"dc_title_s": "J. Block's: Clothing", "ark": "fk4tt4xv5h", "id": "8257", "Geometry Type": "Point", "Location": "Penn Yan, NY", "Year": "null", "Language": "eng", "Street Address (If Available)": "Jacob Street, Penn Yan, Ny", "Subject Terms": "Clothing Trade|Advertising Cards|Jewish Merchants|Jewish Peddlers|Stores, Retail"}}]}