{"type": "FeatureCollection", "features": [{"type": "Feature", "geometry": {"type": "Point", "coordinates": [-75.14035280000002, 39.96268979999999]}, "properties": {"dc_title_s": "Joseph Wm. Itzstein: Tin Roofer, Copper, Tin, And Sheet-iron Worker", "ark": "fk4tb1dx77", "id": "2961", "Geometry Type": "Point", "Location": "Philadelphia, PA", "Year": "null", "Language": "eng", "Street Address (If Available)": "156 Brown Street, Below Second, Philadelphia, Pa", "Subject Terms": "Roofing|Advertising Cards|Jewish Merchants|Jewish Peddlers|Tin|Roofing|Copper|Tinsmithing|Sheet-metal Work"}}]}