{"type": "FeatureCollection", "features": [{"type": "Feature", "geometry": {"type": "Point", "coordinates": [-76.1521334, 43.052375100000006]}, "properties": {"dc_title_s": "Jacob Weinheimer: Furniture And Upholstery Goods", "ark": "fk4tm7j34d", "id": "9253", "Geometry Type": "Point", "Location": "Syracuse, NY", "Year": "null", "Language": "eng", "Street Address (If Available)": "49 North Salina Street, Syracuse, Ny", "Subject Terms": "Furniture Industry And Trade|Advertising Cards|Jewish Merchants|Jewish Peddlers|Upholstery Trade"}}]}