{"type": "FeatureCollection", "features": [{"type": "Feature", "geometry": {"type": "Point", "coordinates": [-78.86445309999999, 42.891906199999994]}, "properties": {"dc_title_s": "Louis F. Moershfelder: Hats, Caps And Gents' Furnishing Goods", "ark": "fk4tm7j35x", "id": "2693", "Geometry Type": "Point", "Location": "Buffalo, NY", "Year": "null", "Language": "eng", "Street Address (If Available)": "277 Genesee Street, Buffalo, Ny", "Subject Terms": "Hat Trade|Advertising Cards|Jewish Merchants|Jewish Peddlers|Men's Furnishing Goods"}}]}