{"type": "FeatureCollection", "features": [{"type": "Feature", "geometry": {"type": "Point", "coordinates": [-76.15217419999999, 43.0507702]}, "properties": {"dc_title_s": "S. Rosenbloom & Sons: Shoe Dealers", "ark": "fk4th8tq1d", "id": "10048", "Geometry Type": "Point", "Location": "Syracuse, NY", "Year": "null", "Language": "eng", "Street Address (If Available)": "Corner Salina And Railroad Streets, Syracuse, Ny", "Subject Terms": "Shoe Industry|Advertising Cards|Jewish Merchants|Jewish Peddlers"}}]}