{"type": "FeatureCollection", "features": [{"type": "Feature", "geometry": {"type": "Point", "coordinates": [-103.76293760000001, 44.350080100000014]}, "properties": {"dc_title_s": "P. Cohen: One Price Clothing", "ark": "fk4v12bn48", "id": "2318", "Geometry Type": "Point", "Location": "Lead City, DT", "Year": "null", "Language": "eng", "Street Address (If Available)": "Mill Street, Lead City, Dt", "Subject Terms": "Clothing Trade|Advertising Cards|Jewish Merchants|Jewish Peddlers|Stores, Retail|Variety Stores"}}]}