{"type": "FeatureCollection", "features": [{"type": "Feature", "geometry": {"type": "Point", "coordinates": [-87.62979819999998, 41.87811360000002]}, "properties": {"dc_title_s": "Sears, Roebuck And Co.: Grocery Building", "ark": "fk4vx0p452", "id": "12157", "Geometry Type": "Point", "Location": "Chicago, IL", "Year": "null", "Language": "eng", "Street Address (If Available)": "Chicago, Il", "Subject Terms": "Grocers|Advertising Cards|Jewish Merchants|Jewish Peddlers|Stores, Retail"}}]}