{"type": "FeatureCollection", "features": [{"type": "Feature", "geometry": {"type": "Point", "coordinates": [-74.8316618, 39.98946720000001]}, "properties": {"dc_title_s": "Emanuel Katz: Dealer In Fashionable Clothing And Gents' Furnishing Goods", "ark": "fk4vm4k06j", "id": "2642", "Geometry Type": "Point", "Location": "Mount Holly, NJ", "Year": "null", "Language": "eng", "Street Address (If Available)": "1121 Broad Street, Corner Of Parkhurst Street, Mt. Holly, Nj", "Subject Terms": "Clothing Trade|Advertising Cards|Jewish Merchants|Jewish Peddlers|Dealers (retail Trade)|Men's Furnishing Goods|Stores, Retail"}}]}