{"type": "FeatureCollection", "features": [{"type": "Feature", "geometry": {"type": "Point", "coordinates": [-77.6123667, 43.15675390000001]}, "properties": {"dc_title_s": "S. Rosenblatt & Co.: Hosier, Underwear, Etc.", "ark": "fk4v41218s", "id": "9444", "Geometry Type": "Point", "Location": "Rochester, NY", "Year": "null", "Language": "eng", "Street Address (If Available)": "42 State Street, Rochester, Ny", "Subject Terms": "Underwear Industry|Advertising Cards|Jewish Merchants|Jewish Peddlers|Hosiery Industry"}}]}