{"type": "FeatureCollection", "features": [{"type": "Feature", "geometry": {"type": "Point", "coordinates": [-74.42171729999998, 39.36569800000001]}, "properties": {"dc_title_s": "Shinnen's: Shoe Store", "ark": "fk4vx0p48m", "id": "5521", "Geometry Type": "Point", "Location": "Atlantic City, NJ", "Year": "null", "Language": "eng", "Street Address (If Available)": "813-1614 Atlantic Avenue, Atlantic City, Nj", "Subject Terms": "Shoe Industry|Advertising Cards|Jewish Merchants|Jewish Peddlers|Stores, Retail|Shoe Store"}}]}