{"type": "FeatureCollection", "features": [{"type": "Feature", "geometry": {"type": "Point", "coordinates": [-84.9047689, 42.870242800000014]}, "properties": {"dc_title_s": "Philip E. Newman & Co.: Boots & Shoes", "ark": "fk4vh5vk53", "id": "13652", "Geometry Type": "Point", "Location": "Grand Rapids, MI", "Year": "null", "Language": "eng", "Street Address (If Available)": "46 Canal Street, Grand Rapids, Mi", "Subject Terms": "Shoe Industry|Advertising Cards|Jewish Merchants|Jewish Peddlers|Boots"}}]}