{"type": "FeatureCollection", "features": [{"type": "Feature", "geometry": {"type": "Point", "coordinates": [-72.5754149, 41.2959908]}, "properties": {"dc_title_s": "R.E. Rice: Dealer In Ice, Vegetables, And Fruits, Hot Bed Plants, Garden Seeds, & C.", "ark": "fk4w09cj7p", "id": "2401", "Geometry Type": "Point", "Location": "Madison, CT", "Year": "null", "Language": "eng", "Street Address (If Available)": "Madison, Ct", "Subject Terms": "Dealers (retail Trade)|Advertising Cards|Jewish Merchants|Jewish Peddlers|Stores, Retail|Fruit Trade|Produce Trade|Vegetable Trade|Seed Industry And Trade|Ice Industry|Plants"}}]}