{"type": "FeatureCollection", "features": [{"type": "Feature", "geometry": {"type": "Point", "coordinates": [-70.21767909999998, 44.0983744]}, "properties": {"dc_title_s": "F. Friedman: Trimmings, Fancy Goods, Toys And Notions", "ark": "fk4w66s945", "id": "12590", "Geometry Type": "Point", "Location": "Lewiston, ME", "Year": "null", "Language": "eng", "Street Address (If Available)": "22 Lisbon Street, Lewiston, Me", "Subject Terms": "Toy Industry|Advertising Cards|Jewish Merchants|Jewish Peddlers|Notions (merchandise)|Notions (merchandise)|Dry-goods|Stores, Retail|Textile Industry"}}]}