{"type": "FeatureCollection", "features": [{"type": "Feature", "geometry": {"type": "Point", "coordinates": [-76.6060918, 39.294589000000016]}, "properties": {"dc_title_s": "S. Katzenberg: Furniture", "ark": "fk4wm1kv77", "id": "12970", "Geometry Type": "Point", "Location": "Baltimore, MD", "Year": "null", "Language": "eng", "Street Address (If Available)": "467 North Gay Street, Baltimore, Md", "Subject Terms": "Furniture Industry And Trade|Advertising Cards|Jewish Merchants|Jewish Peddlers"}}]}