{"type": "FeatureCollection", "features": [{"type": "Feature", "geometry": {"type": "Point", "coordinates": [-73.8865106, 42.236717600000006]}, "properties": {"dc_title_s": "B. Joseph's Sons: Clothiers, Hatters, And Gents Furnishers", "ark": "fk4w66sb2m", "id": "8625", "Geometry Type": "Point", "Location": "Catskill, NY", "Year": "null", "Language": "eng", "Street Address (If Available)": "263 Main Street, Catskill, Ny", "Subject Terms": "Hat Trade|Advertising Cards|Jewish Merchants|Jewish Peddlers|Men's Furnishing Goods|Clothing Trade"}}]}