{"type": "FeatureCollection", "features": [{"type": "Feature", "geometry": {"type": "Point", "coordinates": [-73.6898965, 42.733008900000016]}, "properties": {"dc_title_s": "Tobias: The New York Hatter", "ark": "fk4wh2wh24", "id": "2765", "Geometry Type": "Point", "Location": "Troy, NY", "Year": "null", "Language": "eng", "Street Address (If Available)": "340 River Street, Troy, Ny", "Subject Terms": "Clothing Trade|Advertising Cards|Jewish Merchants|Jewish Peddlers|Hat Trade"}}]}