{"type": "FeatureCollection", "features": [{"type": "Feature", "geometry": {"type": "Point", "coordinates": [-73.6903049, 42.7305568]}, "properties": {"dc_title_s": "W.H. Frear: Dry Goods, Etc.", "ark": "fk4wh2wh45", "id": "9787", "Geometry Type": "Point", "Location": "Troy, NY", "Year": "null", "Language": "eng", "Street Address (If Available)": "Troy Bazaar, Troy, Ny", "Subject Terms": "Dry-goods|Advertising Cards|Jewish Merchants|Jewish Peddlers|Stores, Retail"}}]}