{"type": "FeatureCollection", "features": [{"type": "Feature", "geometry": {"type": "Point", "coordinates": [-88.46509800000001, 42.8097355]}, "properties": {"dc_title_s": "J.A. Schwartz: Gloves, Mittens And Kerosene Oil", "ark": "fk4wm1kv8r", "id": "13835", "Geometry Type": "Point", "Location": "Troy Center, WI", "Year": "null", "Language": "eng", "Street Address (If Available)": "Troy Center, Wi", "Subject Terms": "Glove Industry|Advertising Cards|Jewish Merchants|Jewish Peddlers|Kerosene"}}]}