{"type": "FeatureCollection", "features": [{"type": "Feature", "geometry": {"type": "Point", "coordinates": [-78.87438109999998, 42.88716809999998]}, "properties": {"dc_title_s": "M. Meyersohn: Dealer In Ready-made Clothing, Fine-merchant Tailoring, Gents Furnishing Goods, &c.", "ark": "fk4w382x65", "id": "869", "Geometry Type": "Point", "Location": "Buffalo, NY", "Year": "1886", "Language": "eng", "Street Address (If Available)": "486 Main Street, Buffalo, Ny", "Subject Terms": "Dealers (retail Trade)|Advertising Cards|Jewish Merchants|Jewish Peddlers|Men's Furnishing Goods|Clothing Trade|Ready-to-wear Clothing Industry|Stores, Retail|Textile Industry"}}]}