{"type": "FeatureCollection", "features": [{"type": "Feature", "geometry": {"type": "Point", "coordinates": [-73.7541961, 42.64723169999999]}, "properties": {"dc_title_s": "M.P. Frank: Boots And Shoes", "ark": "fk4xp7b54g", "id": "7253", "Geometry Type": "Point", "Location": "Albany, NY", "Year": "null", "Language": "eng", "Street Address (If Available)": "84 South Pearl Street, Corner Division, Albany, Ny", "Subject Terms": "Shoe Industry|Advertising Cards|Jewish Merchants|Jewish Peddlers|Boots"}}]}