{"type": "FeatureCollection", "features": [{"type": "Feature", "geometry": {"type": "Point", "coordinates": [-74.1715398, 40.7378868]}, "properties": {"dc_title_s": "L.S. Plaut & Co.: The Bee Hive: Largest Dry & Fancy Goods House In New Jersey", "ark": "fk4xs61j50", "id": "5738", "Geometry Type": "Point", "Location": "Newark, NJ", "Year": "null", "Language": "eng", "Street Address (If Available)": "707-721 Broad Street, Newark, Nj", "Subject Terms": "Dry-goods|Advertising Cards|Jewish Merchants|Jewish Peddlers|Stores, Retail|Notions (merchandise)"}}]}