{"type": "FeatureCollection", "features": [{"type": "Feature", "geometry": {"type": "Point", "coordinates": [-73.99746080000001, 40.71401970000001]}, "properties": {"dc_title_s": "Marx Brothers: Gloves, Folding Scissors", "ark": "fk4xw4qx84", "id": "6352", "Geometry Type": "Point", "Location": "New York, NY", "Year": "null", "Language": "eng", "Street Address (If Available)": "1 Division Street, Corner Of Catherine Street, Manhattan, Ny", "Subject Terms": "Glove Industry|Advertising Cards|Jewish Merchants|Jewish Peddlers|Scissors And Shears"}}]}