{"type": "FeatureCollection", "features": [{"type": "Feature", "geometry": {"type": "Point", "coordinates": [-74.0059728, 40.712775300000004]}, "properties": {"dc_title_s": "M. Kohn & Co.: New York Store", "ark": "fk4xs61k2x", "id": "9046", "Geometry Type": "Point", "Location": "New York, NY", "Year": "null", "Language": "eng", "Street Address (If Available)": "New York, Ny", "Subject Terms": "Department Stores|Advertising Cards|Jewish Merchants|Jewish Peddlers|Dry-goods|Notions (merchandise)|Clothing Trade|Textile Industry|Stores, Retail"}}]}