{"type": "FeatureCollection", "features": [{"type": "Feature", "geometry": {"type": "Point", "coordinates": [-73.25320239999999, 42.4494909]}, "properties": {"dc_title_s": "Rosenfeld's: One Price Clothing House", "ark": "fk4x353t26", "id": "13537", "Geometry Type": "Point", "Location": "Pittsfield, MA", "Year": "null", "Language": "eng", "Street Address (If Available)": "64 North Street, Pittsfield, Ma", "Subject Terms": "Clothing Trade|Advertising Cards|Jewish Merchants|Jewish Peddlers|Stores, Retail"}}]}