{"type": "FeatureCollection", "features": [{"type": "Feature", "geometry": {"type": "Point", "coordinates": [-71.0621089, 42.35607830000002]}, "properties": {"dc_title_s": "Ben. Levy & Co.: Levy's Parisian Cream", "ark": "fk4xp7b49k", "id": "13157", "Geometry Type": "Point", "Location": "Boston, MA", "Year": "null", "Language": "eng", "Street Address (If Available)": "58 Winter Street, Boston, Ma", "Subject Terms": "Perfumes Industry|Advertising Cards|Jewish Merchants|Jewish Peddlers|Face--care And Hygiene|Barrier Creams"}}]}