{"type": "FeatureCollection", "features": [{"type": "Feature", "geometry": {"type": "Point", "coordinates": [-76.2407811, 40.60259090000001]}, "properties": {"dc_title_s": "S.H. Mensch: Union House", "ark": "fk4xp7b58j", "id": "2849", "Geometry Type": "Point", "Location": "Friedensburg, PA", "Year": "null", "Language": "eng", "Street Address (If Available)": "Friedensburg, Pa", "Subject Terms": "Hotelkeeper|Advertising Cards|Jewish Merchants|Jewish Peddlers|Stables|Wine Industry|Liquor Industry|Alcoholic Beverage Industry|Bars (drinking Establishments)"}}]}