{"type": "FeatureCollection", "features": [{"type": "Feature", "geometry": {"type": "Point", "coordinates": [-85.76218789999999, 38.255478500000024]}, "properties": {"dc_title_s": "Julius Phillips & Co.: Fine Boots And Shoes", "ark": "fk4xp7b550", "id": "12784", "Geometry Type": "Point", "Location": "Louisville, KY", "Year": "null", "Language": "eng", "Street Address (If Available)": "708 Market Street, 4 Doors Below 7th, Louisville, Ky", "Subject Terms": "Shoe Industry|Advertising Cards|Jewish Merchants|Jewish Peddlers|Boots"}}]}