{"type": "FeatureCollection", "features": [{"type": "Feature", "geometry": {"type": "Point", "coordinates": [-74.17518189999998, 40.736760900000036]}, "properties": {"dc_title_s": "Louis Sacks: Roots & Shoes", "ark": "fk4zs32g00", "id": "5747", "Geometry Type": "Point", "Location": "Newark, NJ", "Year": "null", "Language": "eng", "Street Address (If Available)": "91 Market Street, Opposite Washington, Newark, Nj", "Subject Terms": "Shoe Industry|Advertising Cards|Jewish Merchants|Jewish Peddlers|Boots"}}]}