{"type": "FeatureCollection", "features": [{"type": "Feature", "geometry": {"type": "Point", "coordinates": [-73.98956510000001, 40.73387629999999]}, "properties": {"dc_title_s": "J. Abrahams: New, Old And Rare Books", "ark": "fk4zp4c232", "id": "6259", "Geometry Type": "Point", "Location": "New York, NY", "Year": "null", "Language": "eng", "Street Address (If Available)": "145 Fourth Avenue, Near 14th Street, Manhattan, Ny", "Subject Terms": "Booksellers And Bookselling|Advertising Cards|Jewish Merchants|Jewish Peddlers|Stores, Retail|Bookstores|Antiquarian Booksellers"}}]}